{
  "m_GameObject": {
    "m_FileID": 0,
    "m_PathID": 0
  },
  "m_Enabled": 1,
  "m_Script": {
    "m_FileID": 0,
    "m_PathID": 3652094840918934080
  },
  "m_Name": "jpn_kanji_dp_stickers_info",
  "hash": -1556945896,
  "langID": 1,
  "isResident": 0,
  "isKanji": 1,
  "labelDataArray": [
    {
      "labelIndex": 0,
      "arrayIndex": 0,
      "labelName": "DP_STICKERS_INFO_000",
      "styleInfo": {
        "styleIndex": 109,
        "colorIndex": -1,
        "fontSize": 32,
        "maxWidth": 736,
        "controlID": 0
      },
      "attributeValueArray": [
        -1,
        -1,
        -1,
        -1,
        -1
      ],
      "tagDataArray": [],
      "wordDataArray": [
        {
          "patternID": 7,
          "eventID": 7,
          "tagIndex": -1,
          "tagValue": 0.0,
          "str": "",
          "strWidth": -1.0
        }
      ]
    },
    {
      "labelIndex": 1,
      "arrayIndex": 1,
      "labelName": "DP_STICKERS_INFO_001",
      "styleInfo": {
        "styleIndex": 109,
        "colorIndex": -1,
        "fontSize": 32,
        "maxWidth": 736,
        "controlID": 0
      },
      "attributeValueArray": [
        -1,
        -1,
        -1,
        -1,
        -1
      ],
      "tagDataArray": [],
      "wordDataArray": [
        {
          "patternID": 7,
          "eventID": 1,
          "tagIndex": -1,
          "tagValue": 0.0,
          "str": "ピンクの　小さい　ハートが",
          "strWidth": 406.05
        },
        {
          "patternID": 0,
          "eventID": 7,
          "tagIndex": -1,
          "tagValue": 0.0,
          "str": "浮き上がる　シール",
          "strWidth": 286.0
        }
      ]
    },
    {
      "labelIndex": 2,
      "arrayIndex": 2,
      "labelName": "DP_STICKERS_INFO_002",
      "styleInfo": {
        "styleIndex": 109,
        "colorIndex": -1,
        "fontSize": 32,
        "maxWidth": 736,
        "controlID": 0
      },
      "attributeValueArray": [
        -1,
        -1,
        -1,
        -1,
        -1
      ],
      "tagDataArray": [],
      "wordDataArray": [
        {
          "patternID": 7,
          "eventID": 1,
          "tagIndex": -1,
          "tagValue": 0.0,
          "str": "ピンクの　大きい　ハートが",
          "strWidth": 406.05
        },
        {
          "patternID": 0,
          "eventID": 7,
          "tagIndex": -1,
          "tagValue": 0.0,
          "str": "浮き上がる　シール",
          "strWidth": 286.0
        }
      ]
    },
    {
      "labelIndex": 3,
      "arrayIndex": 3,
      "labelName": "DP_STICKERS_INFO_003",
      "styleInfo": {
        "styleIndex": 109,
        "colorIndex": -1,
        "fontSize": 32,
        "maxWidth": 736,
        "controlID": 0
      },
      "attributeValueArray": [
        -1,
        -1,
        -1,
        -1,
        -1
      ],
      "tagDataArray": [],
      "wordDataArray": [
        {
          "patternID": 7,
          "eventID": 1,
          "tagIndex": -1,
          "tagValue": 0.0,
          "str": "黒く　小さい　ハートが",
          "strWidth": 343.0
        },
        {
          "patternID": 0,
          "eventID": 7,
          "tagIndex": -1,
          "tagValue": 0.0,
          "str": "浮き上がる　シール",
          "strWidth": 286.0
        }
      ]
    },
    {
      "labelIndex": 4,
      "arrayIndex": 4,
      "labelName": "DP_STICKERS_INFO_004",
      "styleInfo": {
        "styleIndex": 109,
        "colorIndex": -1,
        "fontSize": 32,
        "maxWidth": 736,
        "controlID": 0
      },
      "attributeValueArray": [
        -1,
        -1,
        -1,
        -1,
        -1
      ],
      "tagDataArray": [],
      "wordDataArray": [
        {
          "patternID": 7,
          "eventID": 1,
          "tagIndex": -1,
          "tagValue": 0.0,
          "str": "黒く　大きい　ハートが",
          "strWidth": 343.0
        },
        {
          "patternID": 0,
          "eventID": 7,
          "tagIndex": -1,
          "tagValue": 0.0,
          "str": "浮き上がる　シール",
          "strWidth": 286.0
        }
      ]
    },
    {
      "labelIndex": 5,
      "arrayIndex": 5,
      "labelName": "DP_STICKERS_INFO_005",
      "styleInfo": {
        "styleIndex": 109,
        "colorIndex": -1,
        "fontSize": 32,
        "maxWidth": 736,
        "controlID": 0
      },
      "attributeValueArray": [
        -1,
        -1,
        -1,
        -1,
        -1
      ],
      "tagDataArray": [],
      "wordDataArray": [
        {
          "patternID": 7,
          "eventID": 1,
          "tagIndex": -1,
          "tagValue": 0.0,
          "str": "ピンクの　ハートが",
          "strWidth": 279.05
        },
        {
          "patternID": 0,
          "eventID": 7,
          "tagIndex": -1,
          "tagValue": 0.0,
          "str": "ぐるっと　渦巻く　シール",
          "strWidth": 372.95
        }
      ]
    },
    {
      "labelIndex": 6,
      "arrayIndex": 6,
      "labelName": "DP_STICKERS_INFO_006",
      "styleInfo": {
        "styleIndex": 109,
        "colorIndex": -1,
        "fontSize": 32,
        "maxWidth": 736,
        "controlID": 0
      },
      "attributeValueArray": [
        -1,
        -1,
        -1,
        -1,
        -1
      ],
      "tagDataArray": [],
      "wordDataArray": [
        {
          "patternID": 7,
          "eventID": 1,
          "tagIndex": -1,
          "tagValue": 0.0,
          "str": "黒い　ハートが",
          "strWidth": 220.0
        },
        {
          "patternID": 0,
          "eventID": 7,
          "tagIndex": -1,
          "tagValue": 0.0,
          "str": "ぐるっと　渦巻く　シール",
          "strWidth": 372.95
        }
      ]
    },
    {
      "labelIndex": 7,
      "arrayIndex": 7,
      "labelName": "DP_STICKERS_INFO_007",
      "styleInfo": {
        "styleIndex": 109,
        "colorIndex": -1,
        "fontSize": 32,
        "maxWidth": 736,
        "controlID": 0
      },
      "attributeValueArray": [
        -1,
        -1,
        -1,
        -1,
        -1
      ],
      "tagDataArray": [],
      "wordDataArray": [
        {
          "patternID": 7,
          "eventID": 1,
          "tagIndex": -1,
          "tagValue": 0.0,
          "str": "黄色く　小さい　星が",
          "strWidth": 315.0
        },
        {
          "patternID": 0,
          "eventID": 7,
          "tagIndex": -1,
          "tagValue": 0.0,
          "str": "パッと　はじける　シール",
          "strWidth": 376.0
        }
      ]
    },
    {
      "labelIndex": 8,
      "arrayIndex": 8,
      "labelName": "DP_STICKERS_INFO_008",
      "styleInfo": {
        "styleIndex": 109,
        "colorIndex": -1,
        "fontSize": 32,
        "maxWidth": 736,
        "controlID": 0
      },
      "attributeValueArray": [
        -1,
        -1,
        -1,
        -1,
        -1
      ],
      "tagDataArray": [],
      "wordDataArray": [
        {
          "patternID": 7,
          "eventID": 1,
          "tagIndex": -1,
          "tagValue": 0.0,
          "str": "黄色く　大きい　星が",
          "strWidth": 315.0
        },
        {
          "patternID": 0,
          "eventID": 7,
          "tagIndex": -1,
          "tagValue": 0.0,
          "str": "パッと　はじける　シール",
          "strWidth": 376.0
        }
      ]
    },
    {
      "labelIndex": 9,
      "arrayIndex": 9,
      "labelName": "DP_STICKERS_INFO_009",
      "styleInfo": {
        "styleIndex": 109,
        "colorIndex": -1,
        "fontSize": 32,
        "maxWidth": 736,
        "controlID": 0
      },
      "attributeValueArray": [
        -1,
        -1,
        -1,
        -1,
        -1
      ],
      "tagDataArray": [],
      "wordDataArray": [
        {
          "patternID": 7,
          "eventID": 1,
          "tagIndex": -1,
          "tagValue": 0.0,
          "str": "青く　小さい　星が",
          "strWidth": 283.0
        },
        {
          "patternID": 0,
          "eventID": 7,
          "tagIndex": -1,
          "tagValue": 0.0,
          "str": "パッと　はじける　シール",
          "strWidth": 376.0
        }
      ]
    },
    {
      "labelIndex": 10,
      "arrayIndex": 10,
      "labelName": "DP_STICKERS_INFO_010",
      "styleInfo": {
        "styleIndex": 109,
        "colorIndex": -1,
        "fontSize": 32,
        "maxWidth": 736,
        "controlID": 0
      },
      "attributeValueArray": [
        -1,
        -1,
        -1,
        -1,
        -1
      ],
      "tagDataArray": [],
      "wordDataArray": [
        {
          "patternID": 7,
          "eventID": 1,
          "tagIndex": -1,
          "tagValue": 0.0,
          "str": "青く　大きい　星が",
          "strWidth": 283.0
        },
        {
          "patternID": 0,
          "eventID": 7,
          "tagIndex": -1,
          "tagValue": 0.0,
          "str": "パッと　はじける　シール",
          "strWidth": 376.0
        }
      ]
    },
    {
      "labelIndex": 11,
      "arrayIndex": 11,
      "labelName": "DP_STICKERS_INFO_011",
      "styleInfo": {
        "styleIndex": 109,
        "colorIndex": -1,
        "fontSize": 32,
        "maxWidth": 736,
        "controlID": 0
      },
      "attributeValueArray": [
        -1,
        -1,
        -1,
        -1,
        -1
      ],
      "tagDataArray": [],
      "wordDataArray": [
        {
          "patternID": 7,
          "eventID": 1,
          "tagIndex": -1,
          "tagValue": 0.0,
          "str": "小さい　星の　色が　変わりながら",
          "strWidth": 508.95
        },
        {
          "patternID": 0,
          "eventID": 7,
          "tagIndex": -1,
          "tagValue": 0.0,
          "str": "尾を　引いて　降ってくる　シール",
          "strWidth": 495.95
        }
      ]
    },
    {
      "labelIndex": 12,
      "arrayIndex": 12,
      "labelName": "DP_STICKERS_INFO_012",
      "styleInfo": {
        "styleIndex": 109,
        "colorIndex": -1,
        "fontSize": 32,
        "maxWidth": 736,
        "controlID": 0
      },
      "attributeValueArray": [
        -1,
        -1,
        -1,
        -1,
        -1
      ],
      "tagDataArray": [],
      "wordDataArray": [
        {
          "patternID": 7,
          "eventID": 1,
          "tagIndex": -1,
          "tagValue": 0.0,
          "str": "大きい　星の　色が　変わりながら",
          "strWidth": 508.95
        },
        {
          "patternID": 0,
          "eventID": 7,
          "tagIndex": -1,
          "tagValue": 0.0,
          "str": "尾を　引いて　降ってくる　シール",
          "strWidth": 495.95
        }
      ]
    },
    {
      "labelIndex": 13,
      "arrayIndex": 13,
      "labelName": "DP_STICKERS_INFO_013",
      "styleInfo": {
        "styleIndex": 109,
        "colorIndex": -1,
        "fontSize": 32,
        "maxWidth": 736,
        "controlID": 0
      },
      "attributeValueArray": [
        -1,
        -1,
        -1,
        -1,
        -1
      ],
      "tagDataArray": [],
      "wordDataArray": [
        {
          "patternID": 7,
          "eventID": 1,
          "tagIndex": -1,
          "tagValue": 0.0,
          "str": "黄色い　ラインが",
          "strWidth": 252.0
        },
        {
          "patternID": 0,
          "eventID": 7,
          "tagIndex": -1,
          "tagValue": 0.0,
          "str": "広がって　渦巻く　シール",
          "strWidth": 371.95
        }
      ]
    },
    {
      "labelIndex": 14,
      "arrayIndex": 14,
      "labelName": "DP_STICKERS_INFO_014",
      "styleInfo": {
        "styleIndex": 109,
        "colorIndex": -1,
        "fontSize": 32,
        "maxWidth": 736,
        "controlID": 0
      },
      "attributeValueArray": [
        -1,
        -1,
        -1,
        -1,
        -1
      ],
      "tagDataArray": [],
      "wordDataArray": [
        {
          "patternID": 7,
          "eventID": 1,
          "tagIndex": -1,
          "tagValue": 0.0,
          "str": "青い　ラインが",
          "strWidth": 220.0
        },
        {
          "patternID": 0,
          "eventID": 7,
          "tagIndex": -1,
          "tagValue": 0.0,
          "str": "広がって　渦巻く　シール",
          "strWidth": 371.95
        }
      ]
    },
    {
      "labelIndex": 15,
      "arrayIndex": 15,
      "labelName": "DP_STICKERS_INFO_015",
      "styleInfo": {
        "styleIndex": 109,
        "colorIndex": -1,
        "fontSize": 32,
        "maxWidth": 736,
        "controlID": 0
      },
      "attributeValueArray": [
        -1,
        -1,
        -1,
        -1,
        -1
      ],
      "tagDataArray": [],
      "wordDataArray": [
        {
          "patternID": 7,
          "eventID": 1,
          "tagIndex": -1,
          "tagValue": 0.0,
          "str": "赤い　ラインが",
          "strWidth": 220.0
        },
        {
          "patternID": 0,
          "eventID": 7,
          "tagIndex": -1,
          "tagValue": 0.0,
          "str": "広がって　渦巻く　シール",
          "strWidth": 371.95
        }
      ]
    },
    {
      "labelIndex": 16,
      "arrayIndex": 16,
      "labelName": "DP_STICKERS_INFO_016",
      "styleInfo": {
        "styleIndex": 109,
        "colorIndex": -1,
        "fontSize": 32,
        "maxWidth": 736,
        "controlID": 0
      },
      "attributeValueArray": [
        -1,
        -1,
        -1,
        -1,
        -1
      ],
      "tagDataArray": [],
      "wordDataArray": [
        {
          "patternID": 7,
          "eventID": 1,
          "tagIndex": -1,
          "tagValue": 0.0,
          "str": "白い　ラインが",
          "strWidth": 220.0
        },
        {
          "patternID": 0,
          "eventID": 7,
          "tagIndex": -1,
          "tagValue": 0.0,
          "str": "広がって　渦巻く　シール",
          "strWidth": 371.95
        }
      ]
    },
    {
      "labelIndex": 17,
      "arrayIndex": 17,
      "labelName": "DP_STICKERS_INFO_017",
      "styleInfo": {
        "styleIndex": 109,
        "colorIndex": -1,
        "fontSize": 32,
        "maxWidth": 736,
        "controlID": 0
      },
      "attributeValueArray": [
        -1,
        -1,
        -1,
        -1,
        -1
      ],
      "tagDataArray": [],
      "wordDataArray": [
        {
          "patternID": 7,
          "eventID": 1,
          "tagIndex": -1,
          "tagValue": 0.0,
          "str": "白い　煙が",
          "strWidth": 160.0
        },
        {
          "patternID": 0,
          "eventID": 7,
          "tagIndex": -1,
          "tagValue": 0.0,
          "str": "上に　のぼる　シール",
          "strWidth": 318.0
        }
      ]
    },
    {
      "labelIndex": 18,
      "arrayIndex": 18,
      "labelName": "DP_STICKERS_INFO_018",
      "styleInfo": {
        "styleIndex": 109,
        "colorIndex": -1,
        "fontSize": 32,
        "maxWidth": 736,
        "controlID": 0
      },
      "attributeValueArray": [
        -1,
        -1,
        -1,
        -1,
        -1
      ],
      "tagDataArray": [],
      "wordDataArray": [
        {
          "patternID": 7,
          "eventID": 1,
          "tagIndex": -1,
          "tagValue": 0.0,
          "str": "黒い　煙が",
          "strWidth": 160.0
        },
        {
          "patternID": 0,
          "eventID": 7,
          "tagIndex": -1,
          "tagValue": 0.0,
          "str": "上に　のぼる　シール",
          "strWidth": 318.0
        }
      ]
    },
    {
      "labelIndex": 19,
      "arrayIndex": 19,
      "labelName": "DP_STICKERS_INFO_019",
      "styleInfo": {
        "styleIndex": 109,
        "colorIndex": -1,
        "fontSize": 32,
        "maxWidth": 736,
        "controlID": 0
      },
      "attributeValueArray": [
        -1,
        -1,
        -1,
        -1,
        -1
      ],
      "tagDataArray": [],
      "wordDataArray": [
        {
          "patternID": 7,
          "eventID": 1,
          "tagIndex": -1,
          "tagValue": 0.0,
          "str": "白い　煙が",
          "strWidth": 160.0
        },
        {
          "patternID": 0,
          "eventID": 7,
          "tagIndex": -1,
          "tagValue": 0.0,
          "str": "その場で　広がる　シール",
          "strWidth": 381.0
        }
      ]
    },
    {
      "labelIndex": 20,
      "arrayIndex": 20,
      "labelName": "DP_STICKERS_INFO_020",
      "styleInfo": {
        "styleIndex": 109,
        "colorIndex": -1,
        "fontSize": 32,
        "maxWidth": 736,
        "controlID": 0
      },
      "attributeValueArray": [
        -1,
        -1,
        -1,
        -1,
        -1
      ],
      "tagDataArray": [],
      "wordDataArray": [
        {
          "patternID": 7,
          "eventID": 1,
          "tagIndex": -1,
          "tagValue": 0.0,
          "str": "黒い　煙が",
          "strWidth": 160.0
        },
        {
          "patternID": 0,
          "eventID": 7,
          "tagIndex": -1,
          "tagValue": 0.0,
          "str": "その場で　広がる　シール",
          "strWidth": 381.0
        }
      ]
    },
    {
      "labelIndex": 21,
      "arrayIndex": 21,
      "labelName": "DP_STICKERS_INFO_021",
      "styleInfo": {
        "styleIndex": 109,
        "colorIndex": -1,
        "fontSize": 32,
        "maxWidth": 736,
        "controlID": 0
      },
      "attributeValueArray": [
        -1,
        -1,
        -1,
        -1,
        -1
      ],
      "tagDataArray": [],
      "wordDataArray": [
        {
          "patternID": 7,
          "eventID": 1,
          "tagIndex": -1,
          "tagValue": 0.0,
          "str": "びりびりの　電気が",
          "strWidth": 281.9
        },
        {
          "patternID": 0,
          "eventID": 7,
          "tagIndex": -1,
          "tagValue": 0.0,
          "str": "横に　流れる　シール",
          "strWidth": 318.0
        }
      ]
    },
    {
      "labelIndex": 22,
      "arrayIndex": 22,
      "labelName": "DP_STICKERS_INFO_022",
      "styleInfo": {
        "styleIndex": 109,
        "colorIndex": -1,
        "fontSize": 32,
        "maxWidth": 736,
        "controlID": 0
      },
      "attributeValueArray": [
        -1,
        -1,
        -1,
        -1,
        -1
      ],
      "tagDataArray": [],
      "wordDataArray": [
        {
          "patternID": 7,
          "eventID": 1,
          "tagIndex": -1,
          "tagValue": 0.0,
          "str": "びりびりの　電気が",
          "strWidth": 281.9
        },
        {
          "patternID": 0,
          "eventID": 7,
          "tagIndex": -1,
          "tagValue": 0.0,
          "str": "上に　流れる　シール",
          "strWidth": 318.0
        }
      ]
    },
    {
      "labelIndex": 23,
      "arrayIndex": 23,
      "labelName": "DP_STICKERS_INFO_023",
      "styleInfo": {
        "styleIndex": 109,
        "colorIndex": -1,
        "fontSize": 32,
        "maxWidth": 736,
        "controlID": 0
      },
      "attributeValueArray": [
        -1,
        -1,
        -1,
        -1,
        -1
      ],
      "tagDataArray": [],
      "wordDataArray": [
        {
          "patternID": 7,
          "eventID": 1,
          "tagIndex": -1,
          "tagValue": 0.0,
          "str": "びりびりの　電気が",
          "strWidth": 281.9
        },
        {
          "patternID": 0,
          "eventID": 7,
          "tagIndex": -1,
          "tagValue": 0.0,
          "str": "ぐるっと　走る　シール",
          "strWidth": 344.95
        }
      ]
    },
    {
      "labelIndex": 24,
      "arrayIndex": 24,
      "labelName": "DP_STICKERS_INFO_024",
      "styleInfo": {
        "styleIndex": 109,
        "colorIndex": -1,
        "fontSize": 32,
        "maxWidth": 736,
        "controlID": 0
      },
      "attributeValueArray": [
        -1,
        -1,
        -1,
        -1,
        -1
      ],
      "tagDataArray": [],
      "wordDataArray": [
        {
          "patternID": 7,
          "eventID": 1,
          "tagIndex": -1,
          "tagValue": 0.0,
          "str": "びりびりの　電気が",
          "strWidth": 281.9
        },
        {
          "patternID": 0,
          "eventID": 7,
          "tagIndex": -1,
          "tagValue": 0.0,
          "str": "真ん中に　集まる　シール",
          "strWidth": 381.0
        }
      ]
    },
    {
      "labelIndex": 25,
      "arrayIndex": 25,
      "labelName": "DP_STICKERS_INFO_025",
      "styleInfo": {
        "styleIndex": 109,
        "colorIndex": -1,
        "fontSize": 32,
        "maxWidth": 736,
        "controlID": 0
      },
      "attributeValueArray": [
        -1,
        -1,
        -1,
        -1,
        -1
      ],
      "tagDataArray": [],
      "wordDataArray": [
        {
          "patternID": 7,
          "eventID": 1,
          "tagIndex": -1,
          "tagValue": 0.0,
          "str": "青い　泡が",
          "strWidth": 160.0
        },
        {
          "patternID": 0,
          "eventID": 7,
          "tagIndex": -1,
          "tagValue": 0.0,
          "str": "少し　出る　シール",
          "strWidth": 284.0
        }
      ]
    },
    {
      "labelIndex": 26,
      "arrayIndex": 26,
      "labelName": "DP_STICKERS_INFO_026",
      "styleInfo": {
        "styleIndex": 109,
        "colorIndex": -1,
        "fontSize": 32,
        "maxWidth": 736,
        "controlID": 0
      },
      "attributeValueArray": [
        -1,
        -1,
        -1,
        -1,
        -1
      ],
      "tagDataArray": [],
      "wordDataArray": [
        {
          "patternID": 7,
          "eventID": 1,
          "tagIndex": -1,
          "tagValue": 0.0,
          "str": "青い　泡が",
          "strWidth": 160.0
        },
        {
          "patternID": 0,
          "eventID": 7,
          "tagIndex": -1,
          "tagValue": 0.0,
          "str": "たくさん　出る　シール",
          "strWidth": 346.0
        }
      ]
    },
    {
      "labelIndex": 27,
      "arrayIndex": 27,
      "labelName": "DP_STICKERS_INFO_027",
      "styleInfo": {
        "styleIndex": 109,
        "colorIndex": -1,
        "fontSize": 32,
        "maxWidth": 736,
        "controlID": 0
      },
      "attributeValueArray": [
        -1,
        -1,
        -1,
        -1,
        -1
      ],
      "tagDataArray": [],
      "wordDataArray": [
        {
          "patternID": 7,
          "eventID": 1,
          "tagIndex": -1,
          "tagValue": 0.0,
          "str": "ピンクの　泡が",
          "strWidth": 219.05
        },
        {
          "patternID": 0,
          "eventID": 7,
          "tagIndex": -1,
          "tagValue": 0.0,
          "str": "少し　出る　シール",
          "strWidth": 284.0
        }
      ]
    },
    {
      "labelIndex": 28,
      "arrayIndex": 28,
      "labelName": "DP_STICKERS_INFO_028",
      "styleInfo": {
        "styleIndex": 109,
        "colorIndex": -1,
        "fontSize": 32,
        "maxWidth": 736,
        "controlID": 0
      },
      "attributeValueArray": [
        -1,
        -1,
        -1,
        -1,
        -1
      ],
      "tagDataArray": [],
      "wordDataArray": [
        {
          "patternID": 7,
          "eventID": 1,
          "tagIndex": -1,
          "tagValue": 0.0,
          "str": "ピンクの　泡が",
          "strWidth": 219.05
        },
        {
          "patternID": 0,
          "eventID": 7,
          "tagIndex": -1,
          "tagValue": 0.0,
          "str": "たくさん　出る　シール",
          "strWidth": 346.0
        }
      ]
    },
    {
      "labelIndex": 29,
      "arrayIndex": 29,
      "labelName": "DP_STICKERS_INFO_029",
      "styleInfo": {
        "styleIndex": 109,
        "colorIndex": -1,
        "fontSize": 32,
        "maxWidth": 736,
        "controlID": 0
      },
      "attributeValueArray": [
        -1,
        -1,
        -1,
        -1,
        -1
      ],
      "tagDataArray": [],
      "wordDataArray": [
        {
          "patternID": 7,
          "eventID": 1,
          "tagIndex": -1,
          "tagValue": 0.0,
          "str": "赤い　炎が",
          "strWidth": 160.0
        },
        {
          "patternID": 0,
          "eventID": 7,
          "tagIndex": -1,
          "tagValue": 0.0,
          "str": "立ちのぼる　シール",
          "strWidth": 287.0
        }
      ]
    },
    {
      "labelIndex": 30,
      "arrayIndex": 30,
      "labelName": "DP_STICKERS_INFO_030",
      "styleInfo": {
        "styleIndex": 109,
        "colorIndex": -1,
        "fontSize": 32,
        "maxWidth": 736,
        "controlID": 0
      },
      "attributeValueArray": [
        -1,
        -1,
        -1,
        -1,
        -1
      ],
      "tagDataArray": [],
      "wordDataArray": [
        {
          "patternID": 7,
          "eventID": 1,
          "tagIndex": -1,
          "tagValue": 0.0,
          "str": "赤い　炎が",
          "strWidth": 160.0
        },
        {
          "patternID": 0,
          "eventID": 7,
          "tagIndex": -1,
          "tagValue": 0.0,
          "str": "はじけて　広がる　シール",
          "strWidth": 378.0
        }
      ]
    },
    {
      "labelIndex": 31,
      "arrayIndex": 31,
      "labelName": "DP_STICKERS_INFO_031",
      "styleInfo": {
        "styleIndex": 109,
        "colorIndex": -1,
        "fontSize": 32,
        "maxWidth": 736,
        "controlID": 0
      },
      "attributeValueArray": [
        -1,
        -1,
        -1,
        -1,
        -1
      ],
      "tagDataArray": [],
      "wordDataArray": [
        {
          "patternID": 7,
          "eventID": 1,
          "tagIndex": -1,
          "tagValue": 0.0,
          "str": "青い　炎が",
          "strWidth": 160.0
        },
        {
          "patternID": 0,
          "eventID": 7,
          "tagIndex": -1,
          "tagValue": 0.0,
          "str": "立ちのぼる　シール",
          "strWidth": 287.0
        }
      ]
    },
    {
      "labelIndex": 32,
      "arrayIndex": 32,
      "labelName": "DP_STICKERS_INFO_032",
      "styleInfo": {
        "styleIndex": 109,
        "colorIndex": -1,
        "fontSize": 32,
        "maxWidth": 736,
        "controlID": 0
      },
      "attributeValueArray": [
        -1,
        -1,
        -1,
        -1,
        -1
      ],
      "tagDataArray": [],
      "wordDataArray": [
        {
          "patternID": 7,
          "eventID": 1,
          "tagIndex": -1,
          "tagValue": 0.0,
          "str": "青い　炎が",
          "strWidth": 160.0
        },
        {
          "patternID": 0,
          "eventID": 7,
          "tagIndex": -1,
          "tagValue": 0.0,
          "str": "はじけて　広がる　シール",
          "strWidth": 378.0
        }
      ]
    },
    {
      "labelIndex": 33,
      "arrayIndex": 33,
      "labelName": "DP_STICKERS_INFO_033",
      "styleInfo": {
        "styleIndex": 109,
        "colorIndex": -1,
        "fontSize": 32,
        "maxWidth": 736,
        "controlID": 0
      },
      "attributeValueArray": [
        -1,
        -1,
        -1,
        -1,
        -1
      ],
      "tagDataArray": [],
      "wordDataArray": [
        {
          "patternID": 7,
          "eventID": 1,
          "tagIndex": -1,
          "tagValue": 0.0,
          "str": "赤い　紙吹雪が",
          "strWidth": 224.0
        },
        {
          "patternID": 0,
          "eventID": 7,
          "tagIndex": -1,
          "tagValue": 0.0,
          "str": "ひらひら　舞い落ちる　シール",
          "strWidth": 445.0
        }
      ]
    },
    {
      "labelIndex": 34,
      "arrayIndex": 34,
      "labelName": "DP_STICKERS_INFO_034",
      "styleInfo": {
        "styleIndex": 109,
        "colorIndex": -1,
        "fontSize": 32,
        "maxWidth": 736,
        "controlID": 0
      },
      "attributeValueArray": [
        -1,
        -1,
        -1,
        -1,
        -1
      ],
      "tagDataArray": [],
      "wordDataArray": [
        {
          "patternID": 7,
          "eventID": 1,
          "tagIndex": -1,
          "tagValue": 0.0,
          "str": "青い　紙吹雪が",
          "strWidth": 224.0
        },
        {
          "patternID": 0,
          "eventID": 7,
          "tagIndex": -1,
          "tagValue": 0.0,
          "str": "ひらひら　舞い落ちる　シール",
          "strWidth": 445.0
        }
      ]
    },
    {
      "labelIndex": 35,
      "arrayIndex": 35,
      "labelName": "DP_STICKERS_INFO_035",
      "styleInfo": {
        "styleIndex": 109,
        "colorIndex": -1,
        "fontSize": 32,
        "maxWidth": 736,
        "controlID": 0
      },
      "attributeValueArray": [
        -1,
        -1,
        -1,
        -1,
        -1
      ],
      "tagDataArray": [],
      "wordDataArray": [
        {
          "patternID": 7,
          "eventID": 1,
          "tagIndex": -1,
          "tagValue": 0.0,
          "str": "黄色い　紙吹雪が",
          "strWidth": 256.0
        },
        {
          "patternID": 0,
          "eventID": 7,
          "tagIndex": -1,
          "tagValue": 0.0,
          "str": "ひらひら　舞い落ちる　シール",
          "strWidth": 445.0
        }
      ]
    },
    {
      "labelIndex": 36,
      "arrayIndex": 36,
      "labelName": "DP_STICKERS_INFO_036",
      "styleInfo": {
        "styleIndex": 109,
        "colorIndex": -1,
        "fontSize": 32,
        "maxWidth": 736,
        "controlID": 0
      },
      "attributeValueArray": [
        -1,
        -1,
        -1,
        -1,
        -1
      ],
      "tagDataArray": [],
      "wordDataArray": [
        {
          "patternID": 7,
          "eventID": 1,
          "tagIndex": -1,
          "tagValue": 0.0,
          "str": "白い　紙吹雪が",
          "strWidth": 224.0
        },
        {
          "patternID": 0,
          "eventID": 7,
          "tagIndex": -1,
          "tagValue": 0.0,
          "str": "ひらひら　舞い落ちる　シール",
          "strWidth": 445.0
        }
      ]
    },
    {
      "labelIndex": 37,
      "arrayIndex": 37,
      "labelName": "DP_STICKERS_INFO_037",
      "styleInfo": {
        "styleIndex": 109,
        "colorIndex": -1,
        "fontSize": 32,
        "maxWidth": 736,
        "controlID": 0
      },
      "attributeValueArray": [
        -1,
        -1,
        -1,
        -1,
        -1
      ],
      "tagDataArray": [],
      "wordDataArray": [
        {
          "patternID": 7,
          "eventID": 1,
          "tagIndex": -1,
          "tagValue": 0.0,
          "str": "ピンクの　花びらが",
          "strWidth": 282.05
        },
        {
          "patternID": 0,
          "eventID": 7,
          "tagIndex": -1,
          "tagValue": 0.0,
          "str": "ひらひら　舞い落ちる　シール",
          "strWidth": 445.0
        }
      ]
    },
    {
      "labelIndex": 38,
      "arrayIndex": 38,
      "labelName": "DP_STICKERS_INFO_038",
      "styleInfo": {
        "styleIndex": 109,
        "colorIndex": -1,
        "fontSize": 32,
        "maxWidth": 736,
        "controlID": 0
      },
      "attributeValueArray": [
        -1,
        -1,
        -1,
        -1,
        -1
      ],
      "tagDataArray": [],
      "wordDataArray": [
        {
          "patternID": 7,
          "eventID": 1,
          "tagIndex": -1,
          "tagValue": 0.0,
          "str": "ピンクの　花びらが",
          "strWidth": 282.05
        },
        {
          "patternID": 0,
          "eventID": 7,
          "tagIndex": -1,
          "tagValue": 0.0,
          "str": "ぐるっと　渦巻く　シール",
          "strWidth": 372.95
        }
      ]
    },
    {
      "labelIndex": 39,
      "arrayIndex": 39,
      "labelName": "DP_STICKERS_INFO_039",
      "styleInfo": {
        "styleIndex": 109,
        "colorIndex": -1,
        "fontSize": 32,
        "maxWidth": 736,
        "controlID": 0
      },
      "attributeValueArray": [
        -1,
        -1,
        -1,
        -1,
        -1
      ],
      "tagDataArray": [],
      "wordDataArray": [
        {
          "patternID": 7,
          "eventID": 1,
          "tagIndex": -1,
          "tagValue": 0.0,
          "str": "紫の　花びらが",
          "strWidth": 223.0
        },
        {
          "patternID": 0,
          "eventID": 7,
          "tagIndex": -1,
          "tagValue": 0.0,
          "str": "ひらひら　舞い落ちる　シール",
          "strWidth": 445.0
        }
      ]
    },
    {
      "labelIndex": 40,
      "arrayIndex": 40,
      "labelName": "DP_STICKERS_INFO_040",
      "styleInfo": {
        "styleIndex": 109,
        "colorIndex": -1,
        "fontSize": 32,
        "maxWidth": 736,
        "controlID": 0
      },
      "attributeValueArray": [
        -1,
        -1,
        -1,
        -1,
        -1
      ],
      "tagDataArray": [],
      "wordDataArray": [
        {
          "patternID": 7,
          "eventID": 1,
          "tagIndex": -1,
          "tagValue": 0.0,
          "str": "紫の　花びらが",
          "strWidth": 223.0
        },
        {
          "patternID": 0,
          "eventID": 7,
          "tagIndex": -1,
          "tagValue": 0.0,
          "str": "ぐるっと　渦巻く　シール",
          "strWidth": 372.95
        }
      ]
    },
    {
      "labelIndex": 41,
      "arrayIndex": 41,
      "labelName": "DP_STICKERS_INFO_041",
      "styleInfo": {
        "styleIndex": 109,
        "colorIndex": -1,
        "fontSize": 32,
        "maxWidth": 736,
        "controlID": 0
      },
      "attributeValueArray": [
        -1,
        -1,
        -1,
        -1,
        -1
      ],
      "tagDataArray": [],
      "wordDataArray": [
        {
          "patternID": 7,
          "eventID": 1,
          "tagIndex": -1,
          "tagValue": 0.0,
          "str": "黄色い　花びらが",
          "strWidth": 255.0
        },
        {
          "patternID": 0,
          "eventID": 7,
          "tagIndex": -1,
          "tagValue": 0.0,
          "str": "ひらひら　舞い落ちる　シール",
          "strWidth": 445.0
        }
      ]
    },
    {
      "labelIndex": 42,
      "arrayIndex": 42,
      "labelName": "DP_STICKERS_INFO_042",
      "styleInfo": {
        "styleIndex": 109,
        "colorIndex": -1,
        "fontSize": 32,
        "maxWidth": 736,
        "controlID": 0
      },
      "attributeValueArray": [
        -1,
        -1,
        -1,
        -1,
        -1
      ],
      "tagDataArray": [],
      "wordDataArray": [
        {
          "patternID": 7,
          "eventID": 1,
          "tagIndex": -1,
          "tagValue": 0.0,
          "str": "黄色い　花びらが",
          "strWidth": 255.0
        },
        {
          "patternID": 0,
          "eventID": 7,
          "tagIndex": -1,
          "tagValue": 0.0,
          "str": "ぐるっと　渦巻く　シール",
          "strWidth": 372.95
        }
      ]
    },
    {
      "labelIndex": 43,
      "arrayIndex": 43,
      "labelName": "DP_STICKERS_INFO_043",
      "styleInfo": {
        "styleIndex": 109,
        "colorIndex": -1,
        "fontSize": 32,
        "maxWidth": 736,
        "controlID": 0
      },
      "attributeValueArray": [
        -1,
        -1,
        -1,
        -1,
        -1
      ],
      "tagDataArray": [],
      "wordDataArray": [
        {
          "patternID": 7,
          "eventID": 1,
          "tagIndex": -1,
          "tagValue": 0.0,
          "str": "金色の　ト音記号が",
          "strWidth": 284.0
        },
        {
          "patternID": 0,
          "eventID": 7,
          "tagIndex": -1,
          "tagValue": 0.0,
          "str": "くるくる　漂う　シール",
          "strWidth": 341.95
        }
      ]
    },
    {
      "labelIndex": 44,
      "arrayIndex": 44,
      "labelName": "DP_STICKERS_INFO_044",
      "styleInfo": {
        "styleIndex": 109,
        "colorIndex": -1,
        "fontSize": 32,
        "maxWidth": 736,
        "controlID": 0
      },
      "attributeValueArray": [
        -1,
        -1,
        -1,
        -1,
        -1
      ],
      "tagDataArray": [],
      "wordDataArray": [
        {
          "patternID": 7,
          "eventID": 1,
          "tagIndex": -1,
          "tagValue": 0.0,
          "str": "緑の　２分音符が",
          "strWidth": 249.0
        },
        {
          "patternID": 0,
          "eventID": 7,
          "tagIndex": -1,
          "tagValue": 0.0,
          "str": "くるくる　漂う　シール",
          "strWidth": 341.95
        }
      ]
    },
    {
      "labelIndex": 45,
      "arrayIndex": 45,
      "labelName": "DP_STICKERS_INFO_045",
      "styleInfo": {
        "styleIndex": 109,
        "colorIndex": -1,
        "fontSize": 32,
        "maxWidth": 736,
        "controlID": 0
      },
      "attributeValueArray": [
        -1,
        -1,
        -1,
        -1,
        -1
      ],
      "tagDataArray": [],
      "wordDataArray": [
        {
          "patternID": 7,
          "eventID": 1,
          "tagIndex": -1,
          "tagValue": 0.0,
          "str": "赤い　４分音符が",
          "strWidth": 248.95
        },
        {
          "patternID": 0,
          "eventID": 7,
          "tagIndex": -1,
          "tagValue": 0.0,
          "str": "くるくる　漂う　シール",
          "strWidth": 341.95
        }
      ]
    },
    {
      "labelIndex": 46,
      "arrayIndex": 46,
      "labelName": "DP_STICKERS_INFO_046",
      "styleInfo": {
        "styleIndex": 109,
        "colorIndex": -1,
        "fontSize": 32,
        "maxWidth": 736,
        "controlID": 0
      },
      "attributeValueArray": [
        -1,
        -1,
        -1,
        -1,
        -1
      ],
      "tagDataArray": [],
      "wordDataArray": [
        {
          "patternID": 7,
          "eventID": 1,
          "tagIndex": -1,
          "tagValue": 0.0,
          "str": "青い　８分音符が",
          "strWidth": 248.95
        },
        {
          "patternID": 0,
          "eventID": 7,
          "tagIndex": -1,
          "tagValue": 0.0,
          "str": "くるくる　漂う　シール",
          "strWidth": 341.95
        }
      ]
    },
    {
      "labelIndex": 47,
      "arrayIndex": 47,
      "labelName": "DP_STICKERS_INFO_047",
      "styleInfo": {
        "styleIndex": 109,
        "colorIndex": -1,
        "fontSize": 32,
        "maxWidth": 736,
        "controlID": 0
      },
      "attributeValueArray": [
        -1,
        -1,
        -1,
        -1,
        -1
      ],
      "tagDataArray": [],
      "wordDataArray": [
        {
          "patternID": 7,
          "eventID": 1,
          "tagIndex": -1,
          "tagValue": 0.0,
          "str": "カラフルな　２分音符が",
          "strWidth": 340.0
        },
        {
          "patternID": 0,
          "eventID": 7,
          "tagIndex": -1,
          "tagValue": 0.0,
          "str": "くるくる　漂う　シール",
          "strWidth": 341.95
        }
      ]
    },
    {
      "labelIndex": 48,
      "arrayIndex": 48,
      "labelName": "DP_STICKERS_INFO_048",
      "styleInfo": {
        "styleIndex": 109,
        "colorIndex": -1,
        "fontSize": 32,
        "maxWidth": 736,
        "controlID": 0
      },
      "attributeValueArray": [
        -1,
        -1,
        -1,
        -1,
        -1
      ],
      "tagDataArray": [],
      "wordDataArray": [
        {
          "patternID": 7,
          "eventID": 1,
          "tagIndex": -1,
          "tagValue": 0.0,
          "str": "カラフルな　４分音符が",
          "strWidth": 339.95
        },
        {
          "patternID": 0,
          "eventID": 7,
          "tagIndex": -1,
          "tagValue": 0.0,
          "str": "くるくる　漂う　シール",
          "strWidth": 341.95
        }
      ]
    },
    {
      "labelIndex": 49,
      "arrayIndex": 49,
      "labelName": "DP_STICKERS_INFO_049",
      "styleInfo": {
        "styleIndex": 109,
        "colorIndex": -1,
        "fontSize": 32,
        "maxWidth": 736,
        "controlID": 0
      },
      "attributeValueArray": [
        -1,
        -1,
        -1,
        -1,
        -1
      ],
      "tagDataArray": [],
      "wordDataArray": [
        {
          "patternID": 7,
          "eventID": 1,
          "tagIndex": -1,
          "tagValue": 0.0,
          "str": "カラフルな　８分音符が",
          "strWidth": 339.95
        },
        {
          "patternID": 0,
          "eventID": 7,
          "tagIndex": -1,
          "tagValue": 0.0,
          "str": "くるくる　漂う　シール",
          "strWidth": 341.95
        }
      ]
    },
    {
      "labelIndex": 50,
      "arrayIndex": 50,
      "labelName": "DP_STICKERS_INFO_081",
      "styleInfo": {
        "styleIndex": 109,
        "colorIndex": -1,
        "fontSize": 32,
        "maxWidth": 736,
        "controlID": 0
      },
      "attributeValueArray": [
        -1,
        -1,
        -1,
        -1,
        -1
      ],
      "tagDataArray": [],
      "wordDataArray": [
        {
          "patternID": 7,
          "eventID": 1,
          "tagIndex": -1,
          "tagValue": 0.0,
          "str": "毒々しい　霧が",
          "strWidth": 218.0
        },
        {
          "patternID": 0,
          "eventID": 7,
          "tagIndex": -1,
          "tagValue": 0.0,
          "str": "まわりに　吹き出す　シール",
          "strWidth": 409.95
        }
      ]
    },
    {
      "labelIndex": 51,
      "arrayIndex": 51,
      "labelName": "DP_STICKERS_INFO_082",
      "styleInfo": {
        "styleIndex": 109,
        "colorIndex": -1,
        "fontSize": 32,
        "maxWidth": 736,
        "controlID": 0
      },
      "attributeValueArray": [
        -1,
        -1,
        -1,
        -1,
        -1
      ],
      "tagDataArray": [],
      "wordDataArray": [
        {
          "patternID": 7,
          "eventID": 1,
          "tagIndex": -1,
          "tagValue": 0.0,
          "str": "まがまがしい　もやが",
          "strWidth": 315.0
        },
        {
          "patternID": 0,
          "eventID": 7,
          "tagIndex": -1,
          "tagValue": 0.0,
          "str": "まわりに　吹き出す　シール",
          "strWidth": 409.95
        }
      ]
    },
    {
      "labelIndex": 52,
      "arrayIndex": 52,
      "labelName": "DP_STICKERS_INFO_083",
      "styleInfo": {
        "styleIndex": 109,
        "colorIndex": -1,
        "fontSize": 32,
        "maxWidth": 736,
        "controlID": 0
      },
      "attributeValueArray": [
        -1,
        -1,
        -1,
        -1,
        -1
      ],
      "tagDataArray": [],
      "wordDataArray": [
        {
          "patternID": 7,
          "eventID": 1,
          "tagIndex": -1,
          "tagValue": 0.0,
          "str": "なにかが　隠れて　いそうな　煙が",
          "strWidth": 506.900024
        },
        {
          "patternID": 0,
          "eventID": 7,
          "tagIndex": -1,
          "tagValue": 0.0,
          "str": "まわりを　包み込む　シール",
          "strWidth": 411.0
        }
      ]
    },
    {
      "labelIndex": 53,
      "arrayIndex": 53,
      "labelName": "DP_STICKERS_INFO_084",
      "styleInfo": {
        "styleIndex": 109,
        "colorIndex": -1,
        "fontSize": 32,
        "maxWidth": 736,
        "controlID": 0
      },
      "attributeValueArray": [
        -1,
        -1,
        -1,
        -1,
        -1
      ],
      "tagDataArray": [],
      "wordDataArray": [
        {
          "patternID": 7,
          "eventID": 1,
          "tagIndex": -1,
          "tagValue": 0.0,
          "str": "ピンクの　かわいらしい　渦が",
          "strWidth": 440.05
        },
        {
          "patternID": 0,
          "eventID": 7,
          "tagIndex": -1,
          "tagValue": 0.0,
          "str": "まわりに　吹き出す　シール",
          "strWidth": 409.95
        }
      ]
    },
    {
      "labelIndex": 54,
      "arrayIndex": 54,
      "labelName": "DP_STICKERS_INFO_085",
      "styleInfo": {
        "styleIndex": 109,
        "colorIndex": -1,
        "fontSize": 32,
        "maxWidth": 736,
        "controlID": 0
      },
      "attributeValueArray": [
        -1,
        -1,
        -1,
        -1,
        -1
      ],
      "tagDataArray": [],
      "wordDataArray": [
        {
          "patternID": 7,
          "eventID": 1,
          "tagIndex": -1,
          "tagValue": 0.0,
          "str": "カラフルな　リングが",
          "strWidth": 310.1
        },
        {
          "patternID": 0,
          "eventID": 7,
          "tagIndex": -1,
          "tagValue": 0.0,
          "str": "まわりを　漂う　シール",
          "strWidth": 345.95
        }
      ]
    },
    {
      "labelIndex": 55,
      "arrayIndex": 55,
      "labelName": "DP_STICKERS_INFO_086",
      "styleInfo": {
        "styleIndex": 109,
        "colorIndex": -1,
        "fontSize": 32,
        "maxWidth": 736,
        "controlID": 0
      },
      "attributeValueArray": [
        -1,
        -1,
        -1,
        -1,
        -1
      ],
      "tagDataArray": [],
      "wordDataArray": [
        {
          "patternID": 7,
          "eventID": 1,
          "tagIndex": -1,
          "tagValue": 0.0,
          "str": "ピンクの　キラキラが",
          "strWidth": 315.05
        },
        {
          "patternID": 0,
          "eventID": 7,
          "tagIndex": -1,
          "tagValue": 0.0,
          "str": "まわりを　渦巻く　シール",
          "strWidth": 375.0
        }
      ]
    },
    {
      "labelIndex": 56,
      "arrayIndex": 56,
      "labelName": "DP_STICKERS_INFO_087",
      "styleInfo": {
        "styleIndex": 109,
        "colorIndex": -1,
        "fontSize": 32,
        "maxWidth": 736,
        "controlID": 0
      },
      "attributeValueArray": [
        -1,
        -1,
        -1,
        -1,
        -1
      ],
      "tagDataArray": [],
      "wordDataArray": [
        {
          "patternID": 7,
          "eventID": 1,
          "tagIndex": -1,
          "tagValue": 0.0,
          "str": "涼し気な　水の　渦が",
          "strWidth": 317.0
        },
        {
          "patternID": 0,
          "eventID": 7,
          "tagIndex": -1,
          "tagValue": 0.0,
          "str": "まわりを　包み込む　シール",
          "strWidth": 411.0
        }
      ]
    },
    {
      "labelIndex": 57,
      "arrayIndex": 57,
      "labelName": "DP_STICKERS_INFO_088",
      "styleInfo": {
        "styleIndex": 109,
        "colorIndex": -1,
        "fontSize": 32,
        "maxWidth": 736,
        "controlID": 0
      },
      "attributeValueArray": [
        -1,
        -1,
        -1,
        -1,
        -1
      ],
      "tagDataArray": [],
      "wordDataArray": [
        {
          "patternID": 7,
          "eventID": 1,
          "tagIndex": -1,
          "tagValue": 0.0,
          "str": "綺麗な　氷の　刃が",
          "strWidth": 288.0
        },
        {
          "patternID": 0,
          "eventID": 7,
          "tagIndex": -1,
          "tagValue": 0.0,
          "str": "きらめく　シール",
          "strWidth": 250.0
        }
      ]
    },
    {
      "labelIndex": 58,
      "arrayIndex": 58,
      "labelName": "DP_STICKERS_INFO_089",
      "styleInfo": {
        "styleIndex": 109,
        "colorIndex": -1,
        "fontSize": 32,
        "maxWidth": 736,
        "controlID": 0
      },
      "attributeValueArray": [
        -1,
        -1,
        -1,
        -1,
        -1
      ],
      "tagDataArray": [],
      "wordDataArray": [
        {
          "patternID": 7,
          "eventID": 1,
          "tagIndex": -1,
          "tagValue": 0.0,
          "str": "たくさんの　雪の　結晶が",
          "strWidth": 379.0
        },
        {
          "patternID": 0,
          "eventID": 7,
          "tagIndex": -1,
          "tagValue": 0.0,
          "str": "舞い散る　シール",
          "strWidth": 255.0
        }
      ]
    },
    {
      "labelIndex": 59,
      "arrayIndex": 59,
      "labelName": "DP_STICKERS_INFO_090",
      "styleInfo": {
        "styleIndex": 109,
        "colorIndex": -1,
        "fontSize": 32,
        "maxWidth": 736,
        "controlID": 0
      },
      "attributeValueArray": [
        -1,
        -1,
        -1,
        -1,
        -1
      ],
      "tagDataArray": [],
      "wordDataArray": [
        {
          "patternID": 7,
          "eventID": 1,
          "tagIndex": -1,
          "tagValue": 0.0,
          "str": "紅蓮の　炎が",
          "strWidth": 192.0
        },
        {
          "patternID": 0,
          "eventID": 7,
          "tagIndex": -1,
          "tagValue": 0.0,
          "str": "一瞬　燃え盛る　シール",
          "strWidth": 351.0
        }
      ]
    },
    {
      "labelIndex": 60,
      "arrayIndex": 60,
      "labelName": "DP_STICKERS_INFO_091",
      "styleInfo": {
        "styleIndex": 109,
        "colorIndex": -1,
        "fontSize": 32,
        "maxWidth": 736,
        "controlID": 0
      },
      "attributeValueArray": [
        -1,
        -1,
        -1,
        -1,
        -1
      ],
      "tagDataArray": [],
      "wordDataArray": [
        {
          "patternID": 7,
          "eventID": 1,
          "tagIndex": -1,
          "tagValue": 0.0,
          "str": "舞い散る　火の粉が",
          "strWidth": 288.0
        },
        {
          "patternID": 0,
          "eventID": 7,
          "tagIndex": -1,
          "tagValue": 0.0,
          "str": "空から　降りそそぐ　シール",
          "strWidth": 411.95
        }
      ]
    },
    {
      "labelIndex": 61,
      "arrayIndex": 61,
      "labelName": "DP_STICKERS_INFO_092",
      "styleInfo": {
        "styleIndex": 109,
        "colorIndex": -1,
        "fontSize": 32,
        "maxWidth": 736,
        "controlID": 0
      },
      "attributeValueArray": [
        -1,
        -1,
        -1,
        -1,
        -1
      ],
      "tagDataArray": [],
      "wordDataArray": [
        {
          "patternID": 7,
          "eventID": 1,
          "tagIndex": -1,
          "tagValue": 0.0,
          "str": "燃え盛る　火炎が",
          "strWidth": 256.0
        },
        {
          "patternID": 0,
          "eventID": 7,
          "tagIndex": -1,
          "tagValue": 0.0,
          "str": "まわりに　広がる　シール",
          "strWidth": 378.95
        }
      ]
    },
    {
      "labelIndex": 62,
      "arrayIndex": 62,
      "labelName": "DP_STICKERS_INFO_093",
      "styleInfo": {
        "styleIndex": 109,
        "colorIndex": -1,
        "fontSize": 32,
        "maxWidth": 736,
        "controlID": 0
      },
      "attributeValueArray": [
        -1,
        -1,
        -1,
        -1,
        -1
      ],
      "tagDataArray": [],
      "wordDataArray": [
        {
          "patternID": 7,
          "eventID": 1,
          "tagIndex": -1,
          "tagValue": 0.0,
          "str": "空に　舞う　羽根が",
          "strWidth": 285.95
        },
        {
          "patternID": 0,
          "eventID": 7,
          "tagIndex": -1,
          "tagValue": 0.0,
          "str": "大きく　広がる　シール",
          "strWidth": 346.0
        }
      ]
    },
    {
      "labelIndex": 63,
      "arrayIndex": 63,
      "labelName": "DP_STICKERS_INFO_094",
      "styleInfo": {
        "styleIndex": 109,
        "colorIndex": -1,
        "fontSize": 32,
        "maxWidth": 736,
        "controlID": 0
      },
      "attributeValueArray": [
        -1,
        -1,
        -1,
        -1,
        -1
      ],
      "tagDataArray": [],
      "wordDataArray": [
        {
          "patternID": 7,
          "eventID": 1,
          "tagIndex": -1,
          "tagValue": 0.0,
          "str": "澄み切った　風が",
          "strWidth": 252.0
        },
        {
          "patternID": 0,
          "eventID": 7,
          "tagIndex": -1,
          "tagValue": 0.0,
          "str": "そばを　吹き抜ける　シール",
          "strWidth": 413.05
        }
      ]
    },
    {
      "labelIndex": 64,
      "arrayIndex": 64,
      "labelName": "DP_STICKERS_INFO_095",
      "styleInfo": {
        "styleIndex": 109,
        "colorIndex": -1,
        "fontSize": 32,
        "maxWidth": 736,
        "controlID": 0
      },
      "attributeValueArray": [
        -1,
        -1,
        -1,
        -1,
        -1
      ],
      "tagDataArray": [],
      "wordDataArray": [
        {
          "patternID": 7,
          "eventID": 1,
          "tagIndex": -1,
          "tagValue": 0.0,
          "str": "きらめく　りんぷんが",
          "strWidth": 312.95
        },
        {
          "patternID": 0,
          "eventID": 7,
          "tagIndex": -1,
          "tagValue": 0.0,
          "str": "まわりに　渦巻く　シール",
          "strWidth": 374.95
        }
      ]
    },
    {
      "labelIndex": 65,
      "arrayIndex": 65,
      "labelName": "DP_STICKERS_INFO_096",
      "styleInfo": {
        "styleIndex": 109,
        "colorIndex": -1,
        "fontSize": 32,
        "maxWidth": 736,
        "controlID": 0
      },
      "attributeValueArray": [
        -1,
        -1,
        -1,
        -1,
        -1
      ],
      "tagDataArray": [],
      "wordDataArray": [
        {
          "patternID": 7,
          "eventID": 1,
          "tagIndex": -1,
          "tagValue": 0.0,
          "str": "不思議な　磁場が",
          "strWidth": 256.0
        },
        {
          "patternID": 0,
          "eventID": 7,
          "tagIndex": -1,
          "tagValue": 0.0,
          "str": "岩の　欠片を　つなぎとめる　シール",
          "strWidth": 539.0
        }
      ]
    },
    {
      "labelIndex": 66,
      "arrayIndex": 66,
      "labelName": "DP_STICKERS_INFO_097",
      "styleInfo": {
        "styleIndex": 109,
        "colorIndex": -1,
        "fontSize": 32,
        "maxWidth": 736,
        "controlID": 0
      },
      "attributeValueArray": [
        -1,
        -1,
        -1,
        -1,
        -1
      ],
      "tagDataArray": [],
      "wordDataArray": [
        {
          "patternID": 7,
          "eventID": 1,
          "tagIndex": -1,
          "tagValue": 0.0,
          "str": "高速の　隕石が",
          "strWidth": 224.0
        },
        {
          "patternID": 0,
          "eventID": 7,
          "tagIndex": -1,
          "tagValue": 0.0,
          "str": "そばを　通り抜ける　シール",
          "strWidth": 412.0
        }
      ]
    },
    {
      "labelIndex": 67,
      "arrayIndex": 67,
      "labelName": "DP_STICKERS_INFO_098",
      "styleInfo": {
        "styleIndex": 109,
        "colorIndex": -1,
        "fontSize": 32,
        "maxWidth": 736,
        "controlID": 0
      },
      "attributeValueArray": [
        -1,
        -1,
        -1,
        -1,
        -1
      ],
      "tagDataArray": [],
      "wordDataArray": [
        {
          "patternID": 7,
          "eventID": 1,
          "tagIndex": -1,
          "tagValue": 0.0,
          "str": "こまかい　岩の　結晶が",
          "strWidth": 349.0
        },
        {
          "patternID": 0,
          "eventID": 7,
          "tagIndex": -1,
          "tagValue": 0.0,
          "str": "ぐるっと　渦巻く　シール",
          "strWidth": 372.95
        }
      ]
    },
    {
      "labelIndex": 68,
      "arrayIndex": 68,
      "labelName": "DP_STICKERS_INFO_099",
      "styleInfo": {
        "styleIndex": 109,
        "colorIndex": -1,
        "fontSize": 32,
        "maxWidth": 736,
        "controlID": 0
      },
      "attributeValueArray": [
        -1,
        -1,
        -1,
        -1,
        -1
      ],
      "tagDataArray": [],
      "wordDataArray": [
        {
          "patternID": 7,
          "eventID": 1,
          "tagIndex": -1,
          "tagValue": 0.0,
          "str": "四つ葉の　クローバーが",
          "strWidth": 349.1
        },
        {
          "patternID": 0,
          "eventID": 7,
          "tagIndex": -1,
          "tagValue": 0.0,
          "str": "まわりを　漂う　シール",
          "strWidth": 345.95
        }
      ]
    },
    {
      "labelIndex": 69,
      "arrayIndex": 69,
      "labelName": "DP_STICKERS_INFO_100",
      "styleInfo": {
        "styleIndex": 109,
        "colorIndex": -1,
        "fontSize": 32,
        "maxWidth": 736,
        "controlID": 0
      },
      "attributeValueArray": [
        -1,
        -1,
        -1,
        -1,
        -1
      ],
      "tagDataArray": [],
      "wordDataArray": [
        {
          "patternID": 7,
          "eventID": 1,
          "tagIndex": -1,
          "tagValue": 0.0,
          "str": "みずみずしい　若葉が",
          "strWidth": 317.0
        },
        {
          "patternID": 0,
          "eventID": 7,
          "tagIndex": -1,
          "tagValue": 0.0,
          "str": "ひらひら　舞い落ちる　シール",
          "strWidth": 445.0
        }
      ]
    },
    {
      "labelIndex": 70,
      "arrayIndex": 70,
      "labelName": "DP_STICKERS_INFO_101",
      "styleInfo": {
        "styleIndex": 109,
        "colorIndex": -1,
        "fontSize": 32,
        "maxWidth": 736,
        "controlID": 0
      },
      "attributeValueArray": [
        -1,
        -1,
        -1,
        -1,
        -1
      ],
      "tagDataArray": [],
      "wordDataArray": [
        {
          "patternID": 7,
          "eventID": 1,
          "tagIndex": -1,
          "tagValue": 0.0,
          "str": "風に　舞う　葉っぱが",
          "strWidth": 313.95
        },
        {
          "patternID": 0,
          "eventID": 7,
          "tagIndex": -1,
          "tagValue": 0.0,
          "str": "まわりを　包み込む　シール",
          "strWidth": 411.0
        }
      ]
    },
    {
      "labelIndex": 71,
      "arrayIndex": 71,
      "labelName": "DP_STICKERS_INFO_102",
      "styleInfo": {
        "styleIndex": 109,
        "colorIndex": -1,
        "fontSize": 32,
        "maxWidth": 736,
        "controlID": 0
      },
      "attributeValueArray": [
        -1,
        -1,
        -1,
        -1,
        -1
      ],
      "tagDataArray": [],
      "wordDataArray": [
        {
          "patternID": 7,
          "eventID": 1,
          "tagIndex": -1,
          "tagValue": 0.0,
          "str": "鋭い　稲妻が",
          "strWidth": 192.0
        },
        {
          "patternID": 0,
          "eventID": 7,
          "tagIndex": -1,
          "tagValue": 0.0,
          "str": "そばを　走り抜ける　シール",
          "strWidth": 412.0
        }
      ]
    },
    {
      "labelIndex": 72,
      "arrayIndex": 72,
      "labelName": "DP_STICKERS_INFO_103",
      "styleInfo": {
        "styleIndex": 109,
        "colorIndex": -1,
        "fontSize": 32,
        "maxWidth": 736,
        "controlID": 0
      },
      "attributeValueArray": [
        -1,
        -1,
        -1,
        -1,
        -1
      ],
      "tagDataArray": [],
      "wordDataArray": [
        {
          "patternID": 7,
          "eventID": 1,
          "tagIndex": -1,
          "tagValue": 0.0,
          "str": "鋭い　稲妻が",
          "strWidth": 192.0
        },
        {
          "patternID": 0,
          "eventID": 7,
          "tagIndex": -1,
          "tagValue": 0.0,
          "str": "外に　走り出る　シール",
          "strWidth": 347.95
        }
      ]
    },
    {
      "labelIndex": 73,
      "arrayIndex": 73,
      "labelName": "DP_STICKERS_INFO_104",
      "styleInfo": {
        "styleIndex": 109,
        "colorIndex": -1,
        "fontSize": 32,
        "maxWidth": 736,
        "controlID": 0
      },
      "attributeValueArray": [
        -1,
        -1,
        -1,
        -1,
        -1
      ],
      "tagDataArray": [],
      "wordDataArray": [
        {
          "patternID": 7,
          "eventID": 1,
          "tagIndex": -1,
          "tagValue": 0.0,
          "str": "電撃の　ボールが",
          "strWidth": 256.0
        },
        {
          "patternID": 0,
          "eventID": 7,
          "tagIndex": -1,
          "tagValue": 0.0,
          "str": "まわりを　漂う　シール",
          "strWidth": 345.95
        }
      ]
    },
    {
      "labelIndex": 74,
      "arrayIndex": 74,
      "labelName": "DP_STICKERS_INFO_105",
      "styleInfo": {
        "styleIndex": 109,
        "colorIndex": -1,
        "fontSize": 32,
        "maxWidth": 736,
        "controlID": 0
      },
      "attributeValueArray": [
        -1,
        -1,
        -1,
        -1,
        -1
      ],
      "tagDataArray": [],
      "wordDataArray": [
        {
          "patternID": 7,
          "eventID": 1,
          "tagIndex": -1,
          "tagValue": 0.0,
          "str": "素敵な　スタイルを　すべて",
          "strWidth": 409.0
        },
        {
          "patternID": 0,
          "eventID": 7,
          "tagIndex": -1,
          "tagValue": 0.0,
          "str": "持つものに　贈られる　シール",
          "strWidth": 445.0
        }
      ]
    },
    {
      "labelIndex": 75,
      "arrayIndex": 75,
      "labelName": "DP_STICKERS_INFO_106",
      "styleInfo": {
        "styleIndex": 109,
        "colorIndex": -1,
        "fontSize": 32,
        "maxWidth": 736,
        "controlID": 0
      },
      "attributeValueArray": [
        -1,
        -1,
        -1,
        -1,
        -1
      ],
      "tagDataArray": [],
      "wordDataArray": [
        {
          "patternID": 7,
          "eventID": 1,
          "tagIndex": -1,
          "tagValue": 0.0,
          "str": "かっこいい　光が",
          "strWidth": 250.0
        },
        {
          "patternID": 0,
          "eventID": 7,
          "tagIndex": -1,
          "tagValue": 0.0,
          "str": "まわりを　きらめく　シール",
          "strWidth": 406.0
        }
      ]
    },
    {
      "labelIndex": 76,
      "arrayIndex": 76,
      "labelName": "DP_STICKERS_INFO_107",
      "styleInfo": {
        "styleIndex": 109,
        "colorIndex": -1,
        "fontSize": 32,
        "maxWidth": 736,
        "controlID": 0
      },
      "attributeValueArray": [
        -1,
        -1,
        -1,
        -1,
        -1
      ],
      "tagDataArray": [],
      "wordDataArray": [
        {
          "patternID": 7,
          "eventID": 1,
          "tagIndex": -1,
          "tagValue": 0.0,
          "str": "かっこいい　光が",
          "strWidth": 250.0
        },
        {
          "patternID": 0,
          "eventID": 7,
          "tagIndex": -1,
          "tagValue": 0.0,
          "str": "空に　舞い上がる　シール",
          "strWidth": 382.0
        }
      ]
    },
    {
      "labelIndex": 77,
      "arrayIndex": 77,
      "labelName": "DP_STICKERS_INFO_108",
      "styleInfo": {
        "styleIndex": 109,
        "colorIndex": -1,
        "fontSize": 32,
        "maxWidth": 736,
        "controlID": 0
      },
      "attributeValueArray": [
        -1,
        -1,
        -1,
        -1,
        -1
      ],
      "tagDataArray": [],
      "wordDataArray": [
        {
          "patternID": 7,
          "eventID": 1,
          "tagIndex": -1,
          "tagValue": 0.0,
          "str": "かっこいい　光が",
          "strWidth": 250.0
        },
        {
          "patternID": 0,
          "eventID": 7,
          "tagIndex": -1,
          "tagValue": 0.0,
          "str": "一瞬　はじける　シール",
          "strWidth": 349.05
        }
      ]
    },
    {
      "labelIndex": 78,
      "arrayIndex": 78,
      "labelName": "DP_STICKERS_INFO_109",
      "styleInfo": {
        "styleIndex": 109,
        "colorIndex": -1,
        "fontSize": 32,
        "maxWidth": 736,
        "controlID": 0
      },
      "attributeValueArray": [
        -1,
        -1,
        -1,
        -1,
        -1
      ],
      "tagDataArray": [],
      "wordDataArray": [
        {
          "patternID": 7,
          "eventID": 1,
          "tagIndex": -1,
          "tagValue": 0.0,
          "str": "かっこいい　光が",
          "strWidth": 250.0
        },
        {
          "patternID": 0,
          "eventID": 7,
          "tagIndex": -1,
          "tagValue": 0.0,
          "str": "一閃する　シール",
          "strWidth": 255.0
        }
      ]
    },
    {
      "labelIndex": 79,
      "arrayIndex": 79,
      "labelName": "DP_STICKERS_INFO_110",
      "styleInfo": {
        "styleIndex": 109,
        "colorIndex": -1,
        "fontSize": 32,
        "maxWidth": 736,
        "controlID": 0
      },
      "attributeValueArray": [
        -1,
        -1,
        -1,
        -1,
        -1
      ],
      "tagDataArray": [],
      "wordDataArray": [
        {
          "patternID": 7,
          "eventID": 1,
          "tagIndex": -1,
          "tagValue": 0.0,
          "str": "美しい　ピンクの　花火が",
          "strWidth": 376.05
        },
        {
          "patternID": 0,
          "eventID": 7,
          "tagIndex": -1,
          "tagValue": 0.0,
          "str": "小さく　はじける　シール",
          "strWidth": 376.05
        }
      ]
    },
    {
      "labelIndex": 80,
      "arrayIndex": 80,
      "labelName": "DP_STICKERS_INFO_111",
      "styleInfo": {
        "styleIndex": 109,
        "colorIndex": -1,
        "fontSize": 32,
        "maxWidth": 736,
        "controlID": 0
      },
      "attributeValueArray": [
        -1,
        -1,
        -1,
        -1,
        -1
      ],
      "tagDataArray": [],
      "wordDataArray": [
        {
          "patternID": 7,
          "eventID": 1,
          "tagIndex": -1,
          "tagValue": 0.0,
          "str": "美しい　緑の　花火が",
          "strWidth": 317.0
        },
        {
          "patternID": 0,
          "eventID": 7,
          "tagIndex": -1,
          "tagValue": 0.0,
          "str": "大きく　はじける　シール",
          "strWidth": 376.05
        }
      ]
    },
    {
      "labelIndex": 81,
      "arrayIndex": 81,
      "labelName": "DP_STICKERS_INFO_112",
      "styleInfo": {
        "styleIndex": 109,
        "colorIndex": -1,
        "fontSize": 32,
        "maxWidth": 736,
        "controlID": 0
      },
      "attributeValueArray": [
        -1,
        -1,
        -1,
        -1,
        -1
      ],
      "tagDataArray": [],
      "wordDataArray": [
        {
          "patternID": 7,
          "eventID": 1,
          "tagIndex": -1,
          "tagValue": 0.0,
          "str": "美しい　カラフルな　花火が",
          "strWidth": 408.0
        },
        {
          "patternID": 0,
          "eventID": 7,
          "tagIndex": -1,
          "tagValue": 0.0,
          "str": "とても　大きく　はじける　シール",
          "strWidth": 499.949982
        }
      ]
    },
    {
      "labelIndex": 82,
      "arrayIndex": 82,
      "labelName": "DP_STICKERS_INFO_113",
      "styleInfo": {
        "styleIndex": 109,
        "colorIndex": -1,
        "fontSize": 32,
        "maxWidth": 736,
        "controlID": 0
      },
      "attributeValueArray": [
        -1,
        -1,
        -1,
        -1,
        -1
      ],
      "tagDataArray": [],
      "wordDataArray": [
        {
          "patternID": 7,
          "eventID": 1,
          "tagIndex": -1,
          "tagValue": 0.0,
          "str": "美しい　カラフルな　光の　粒が",
          "strWidth": 472.0
        },
        {
          "patternID": 0,
          "eventID": 7,
          "tagIndex": -1,
          "tagValue": 0.0,
          "str": "空に　広がる　シール",
          "strWidth": 318.0
        }
      ]
    },
    {
      "labelIndex": 83,
      "arrayIndex": 83,
      "labelName": "DP_STICKERS_INFO_114",
      "styleInfo": {
        "styleIndex": 109,
        "colorIndex": -1,
        "fontSize": 32,
        "maxWidth": 736,
        "controlID": 0
      },
      "attributeValueArray": [
        -1,
        -1,
        -1,
        -1,
        -1
      ],
      "tagDataArray": [],
      "wordDataArray": [
        {
          "patternID": 7,
          "eventID": 1,
          "tagIndex": -1,
          "tagValue": 0.0,
          "str": "かしこい　多面体が",
          "strWidth": 283.0
        },
        {
          "patternID": 0,
          "eventID": 7,
          "tagIndex": -1,
          "tagValue": 0.0,
          "str": "くるくる　まわる　シール",
          "strWidth": 374.0
        }
      ]
    },
    {
      "labelIndex": 84,
      "arrayIndex": 84,
      "labelName": "DP_STICKERS_INFO_115",
      "styleInfo": {
        "styleIndex": 109,
        "colorIndex": -1,
        "fontSize": 32,
        "maxWidth": 736,
        "controlID": 0
      },
      "attributeValueArray": [
        -1,
        -1,
        -1,
        -1,
        -1
      ],
      "tagDataArray": [],
      "wordDataArray": [
        {
          "patternID": 7,
          "eventID": 1,
          "tagIndex": -1,
          "tagValue": 0.0,
          "str": "かしこい　エナジーボールが",
          "strWidth": 410.0
        },
        {
          "patternID": 0,
          "eventID": 7,
          "tagIndex": -1,
          "tagValue": 0.0,
          "str": "くるくる　まわる　シール",
          "strWidth": 374.0
        }
      ]
    },
    {
      "labelIndex": 85,
      "arrayIndex": 85,
      "labelName": "DP_STICKERS_INFO_116",
      "styleInfo": {
        "styleIndex": 109,
        "colorIndex": -1,
        "fontSize": 32,
        "maxWidth": 736,
        "controlID": 0
      },
      "attributeValueArray": [
        -1,
        -1,
        -1,
        -1,
        -1
      ],
      "tagDataArray": [],
      "wordDataArray": [
        {
          "patternID": 7,
          "eventID": 1,
          "tagIndex": -1,
          "tagValue": 0.0,
          "str": "かしこい　光線が",
          "strWidth": 251.0
        },
        {
          "patternID": 0,
          "eventID": 7,
          "tagIndex": -1,
          "tagValue": 0.0,
          "str": "上に　伸びていく　シール",
          "strWidth": 373.95
        }
      ]
    },
    {
      "labelIndex": 86,
      "arrayIndex": 86,
      "labelName": "DP_STICKERS_INFO_117",
      "styleInfo": {
        "styleIndex": 109,
        "colorIndex": -1,
        "fontSize": 32,
        "maxWidth": 736,
        "controlID": 0
      },
      "attributeValueArray": [
        -1,
        -1,
        -1,
        -1,
        -1
      ],
      "tagDataArray": [],
      "wordDataArray": [
        {
          "patternID": 7,
          "eventID": 1,
          "tagIndex": -1,
          "tagValue": 0.0,
          "str": "かしこい　円盤が",
          "strWidth": 251.0
        },
        {
          "patternID": 0,
          "eventID": 7,
          "tagIndex": -1,
          "tagValue": 0.0,
          "str": "いくつか　せり上がる　シール",
          "strWidth": 439.95
        }
      ]
    },
    {
      "labelIndex": 87,
      "arrayIndex": 87,
      "labelName": "DP_STICKERS_INFO_118",
      "styleInfo": {
        "styleIndex": 109,
        "colorIndex": -1,
        "fontSize": 32,
        "maxWidth": 736,
        "controlID": 0
      },
      "attributeValueArray": [
        -1,
        -1,
        -1,
        -1,
        -1
      ],
      "tagDataArray": [],
      "wordDataArray": [
        {
          "patternID": 7,
          "eventID": 1,
          "tagIndex": -1,
          "tagValue": 0.0,
          "str": "たくましい　岩の　欠片が",
          "strWidth": 376.0
        },
        {
          "patternID": 0,
          "eventID": 7,
          "tagIndex": -1,
          "tagValue": 0.0,
          "str": "外に　はじけ飛ぶ　シール",
          "strWidth": 380.05
        }
      ]
    },
    {
      "labelIndex": 88,
      "arrayIndex": 88,
      "labelName": "DP_STICKERS_INFO_119",
      "styleInfo": {
        "styleIndex": 109,
        "colorIndex": -1,
        "fontSize": 32,
        "maxWidth": 736,
        "controlID": 0
      },
      "attributeValueArray": [
        -1,
        -1,
        -1,
        -1,
        -1
      ],
      "tagDataArray": [],
      "wordDataArray": [
        {
          "patternID": 7,
          "eventID": 1,
          "tagIndex": -1,
          "tagValue": 0.0,
          "str": "たくましい　光の　柱が",
          "strWidth": 344.0
        },
        {
          "patternID": 0,
          "eventID": 7,
          "tagIndex": -1,
          "tagValue": 0.0,
          "str": "石を　巻き上げる　シール",
          "strWidth": 381.05
        }
      ]
    },
    {
      "labelIndex": 89,
      "arrayIndex": 89,
      "labelName": "DP_STICKERS_INFO_120",
      "styleInfo": {
        "styleIndex": 109,
        "colorIndex": -1,
        "fontSize": 32,
        "maxWidth": 736,
        "controlID": 0
      },
      "attributeValueArray": [
        -1,
        -1,
        -1,
        -1,
        -1
      ],
      "tagDataArray": [],
      "wordDataArray": [
        {
          "patternID": 7,
          "eventID": 1,
          "tagIndex": -1,
          "tagValue": 0.0,
          "str": "たくましい　砂嵐が",
          "strWidth": 280.0
        },
        {
          "patternID": 0,
          "eventID": 7,
          "tagIndex": -1,
          "tagValue": 0.0,
          "str": "まわりに　渦巻く　シール",
          "strWidth": 374.95
        }
      ]
    },
    {
      "labelIndex": 90,
      "arrayIndex": 90,
      "labelName": "DP_STICKERS_INFO_121",
      "styleInfo": {
        "styleIndex": 109,
        "colorIndex": -1,
        "fontSize": 32,
        "maxWidth": 736,
        "controlID": 0
      },
      "attributeValueArray": [
        -1,
        -1,
        -1,
        -1,
        -1
      ],
      "tagDataArray": [],
      "wordDataArray": [
        {
          "patternID": 7,
          "eventID": 1,
          "tagIndex": -1,
          "tagValue": 0.0,
          "str": "たくましい　砂煙が",
          "strWidth": 280.0
        },
        {
          "patternID": 0,
          "eventID": 7,
          "tagIndex": -1,
          "tagValue": 0.0,
          "str": "その場で　巻き上がる　シール",
          "strWidth": 444.0
        }
      ]
    },
    {
      "labelIndex": 91,
      "arrayIndex": 91,
      "labelName": "DP_STICKERS_INFO_122",
      "styleInfo": {
        "styleIndex": 109,
        "colorIndex": -1,
        "fontSize": 32,
        "maxWidth": 736,
        "controlID": 0
      },
      "attributeValueArray": [
        -1,
        -1,
        -1,
        -1,
        -1
      ],
      "tagDataArray": [],
      "wordDataArray": [
        {
          "patternID": 7,
          "eventID": 1,
          "tagIndex": -1,
          "tagValue": 0.0,
          "str": "かわいい　シャボン玉が",
          "strWidth": 347.0
        },
        {
          "patternID": 0,
          "eventID": 7,
          "tagIndex": -1,
          "tagValue": 0.0,
          "str": "空に　飛んでいく　シール",
          "strWidth": 376.0
        }
      ]
    },
    {
      "labelIndex": 92,
      "arrayIndex": 92,
      "labelName": "DP_STICKERS_INFO_123",
      "styleInfo": {
        "styleIndex": 109,
        "colorIndex": -1,
        "fontSize": 32,
        "maxWidth": 736,
        "controlID": 0
      },
      "attributeValueArray": [
        -1,
        -1,
        -1,
        -1,
        -1
      ],
      "tagDataArray": [],
      "wordDataArray": [
        {
          "patternID": 7,
          "eventID": 1,
          "tagIndex": -1,
          "tagValue": 0.0,
          "str": "かわいい　キャンディが",
          "strWidth": 342.95
        },
        {
          "patternID": 0,
          "eventID": 7,
          "tagIndex": -1,
          "tagValue": 0.0,
          "str": "外に　はじけ飛ぶ　シール",
          "strWidth": 380.05
        }
      ]
    },
    {
      "labelIndex": 93,
      "arrayIndex": 93,
      "labelName": "DP_STICKERS_INFO_124",
      "styleInfo": {
        "styleIndex": 109,
        "colorIndex": -1,
        "fontSize": 32,
        "maxWidth": 736,
        "controlID": 0
      },
      "attributeValueArray": [
        -1,
        -1,
        -1,
        -1,
        -1
      ],
      "tagDataArray": [],
      "wordDataArray": [
        {
          "patternID": 7,
          "eventID": 1,
          "tagIndex": -1,
          "tagValue": 0.0,
          "str": "かわいい　キャンディが",
          "strWidth": 342.95
        },
        {
          "patternID": 0,
          "eventID": 7,
          "tagIndex": -1,
          "tagValue": 0.0,
          "str": "外に　こぼれ落ちる　シール",
          "strWidth": 412.0
        }
      ]
    },
    {
      "labelIndex": 94,
      "arrayIndex": 94,
      "labelName": "DP_STICKERS_INFO_125",
      "styleInfo": {
        "styleIndex": 109,
        "colorIndex": -1,
        "fontSize": 32,
        "maxWidth": 736,
        "controlID": 0
      },
      "attributeValueArray": [
        -1,
        -1,
        -1,
        -1,
        -1
      ],
      "tagDataArray": [],
      "wordDataArray": [
        {
          "patternID": 7,
          "eventID": 1,
          "tagIndex": -1,
          "tagValue": 0.0,
          "str": "かわいい　虹が",
          "strWidth": 224.0
        },
        {
          "patternID": 0,
          "eventID": 7,
          "tagIndex": -1,
          "tagValue": 0.0,
          "str": "ぐるっと　渦巻く　シール",
          "strWidth": 372.95
        }
      ]
    },
    {
      "labelIndex": 95,
      "arrayIndex": 95,
      "labelName": "DP_STICKERS_INFO_126",
      "styleInfo": {
        "styleIndex": 109,
        "colorIndex": -1,
        "fontSize": 32,
        "maxWidth": 736,
        "controlID": 0
      },
      "attributeValueArray": [
        -1,
        -1,
        -1,
        -1,
        -1
      ],
      "tagDataArray": [],
      "wordDataArray": [
        {
          "patternID": 7,
          "eventID": 1,
          "tagIndex": -1,
          "tagValue": 0.0,
          "str": "スーパーコンテストショー！を",
          "strWidth": 420.0
        },
        {
          "patternID": 0,
          "eventID": 7,
          "tagIndex": -1,
          "tagValue": 0.0,
          "str": "極めた　ものに　贈られる　シール",
          "strWidth": 510.0
        }
      ]
    },
    {
      "labelIndex": 96,
      "arrayIndex": 96,
      "labelName": "DP_STICKERS_INFO_135",
      "styleInfo": {
        "styleIndex": 109,
        "colorIndex": -1,
        "fontSize": 32,
        "maxWidth": 736,
        "controlID": 0
      },
      "attributeValueArray": [
        -1,
        -1,
        -1,
        -1,
        -1
      ],
      "tagDataArray": [],
      "wordDataArray": [
        {
          "patternID": 7,
          "eventID": 1,
          "tagIndex": -1,
          "tagValue": 0.0,
          "str": "チャンピオンが　認めた　ものに",
          "strWidth": 471.95
        },
        {
          "patternID": 0,
          "eventID": 7,
          "tagIndex": -1,
          "tagValue": 0.0,
          "str": "贈られる　シール",
          "strWidth": 255.0
        }
      ]
    }
  ]
}