{
  "m_GameObject": {
    "m_FileID": 0,
    "m_PathID": 0
  },
  "m_Enabled": 1,
  "m_Script": {
    "m_FileID": 0,
    "m_PathID": 3652094840918934080
  },
  "m_Name": "french_ss_xmenu_net",
  "hash": -862805692,
  "langID": 3,
  "isResident": 0,
  "isKanji": 0,
  "labelDataArray": [
    {
      "labelIndex": 0,
      "arrayIndex": 0,
      "labelName": "SS_xmenu_net_02",
      "styleInfo": {
        "styleIndex": 50,
        "colorIndex": -1,
        "fontSize": 42,
        "maxWidth": 756,
        "controlID": 0
      },
      "attributeValueArray": [
        0,
        0,
        0,
        0,
        0
      ],
      "tagDataArray": [],
      "wordDataArray": [
        {
          "patternID": 0,
          "eventID": 7,
          "tagIndex": -1,
          "tagValue": 0.0,
          "str": "Pokémon capturés (%)",
          "strWidth": 292.078125
        }
      ]
    },
    {
      "labelIndex": 1,
      "arrayIndex": 1,
      "labelName": "SS_xmenu_net_03",
      "styleInfo": {
        "styleIndex": 50,
        "colorIndex": -1,
        "fontSize": 42,
        "maxWidth": 756,
        "controlID": 0
      },
      "attributeValueArray": [
        0,
        0,
        0,
        0,
        0
      ],
      "tagDataArray": [],
      "wordDataArray": [
        {
          "patternID": 0,
          "eventID": 7,
          "tagIndex": -1,
          "tagValue": 0.0,
          "str": "Évolutions (%)",
          "strWidth": 186.8125
        }
      ]
    },
    {
      "labelIndex": 2,
      "arrayIndex": 2,
      "labelName": "SS_xmenu_net_04",
      "styleInfo": {
        "styleIndex": 50,
        "colorIndex": -1,
        "fontSize": 42,
        "maxWidth": 756,
        "controlID": 0
      },
      "attributeValueArray": [
        0,
        0,
        0,
        0,
        0
      ],
      "tagDataArray": [],
      "wordDataArray": [
        {
          "patternID": 0,
          "eventID": 7,
          "tagIndex": -1,
          "tagValue": 0.0,
          "str": "Œufs éclos (%)",
          "strWidth": 195.078125
        }
      ]
    },
    {
      "labelIndex": 3,
      "arrayIndex": 3,
      "labelName": "SS_xmenu_net_05",
      "styleInfo": {
        "styleIndex": 50,
        "colorIndex": -1,
        "fontSize": 42,
        "maxWidth": 756,
        "controlID": 0
      },
      "attributeValueArray": [
        0,
        0,
        0,
        0,
        0
      ],
      "tagDataArray": [],
      "wordDataArray": [
        {
          "patternID": 0,
          "eventID": 7,
          "tagIndex": -1,
          "tagValue": 0.0,
          "str": "Combats en réseau (%)",
          "strWidth": 301.578125
        }
      ]
    },
    {
      "labelIndex": 4,
      "arrayIndex": 4,
      "labelName": "SS_xmenu_net_06",
      "styleInfo": {
        "styleIndex": 50,
        "colorIndex": -1,
        "fontSize": 42,
        "maxWidth": 756,
        "controlID": 0
      },
      "attributeValueArray": [
        0,
        0,
        0,
        0,
        0
      ],
      "tagDataArray": [],
      "wordDataArray": [
        {
          "patternID": 0,
          "eventID": 7,
          "tagIndex": -1,
          "tagValue": 0.0,
          "str": "Échanges (%)",
          "strWidth": 174.390625
        }
      ]
    },
    {
      "labelIndex": 5,
      "arrayIndex": 5,
      "labelName": "SS_xmenu_net_14",
      "styleInfo": {
        "styleIndex": 50,
        "colorIndex": -1,
        "fontSize": 42,
        "maxWidth": 756,
        "controlID": 0
      },
      "attributeValueArray": [
        0,
        0,
        0,
        0,
        0
      ],
      "tagDataArray": [],
      "wordDataArray": [
        {
          "patternID": 0,
          "eventID": 7,
          "tagIndex": -1,
          "tagValue": 0.0,
          "str": "Accélérations à vélo (%)",
          "strWidth": 316.703125
        }
      ]
    },
    {
      "labelIndex": 6,
      "arrayIndex": 6,
      "labelName": "SS_xmenu_net_15",
      "styleInfo": {
        "styleIndex": 50,
        "colorIndex": -1,
        "fontSize": 42,
        "maxWidth": 756,
        "controlID": 0
      },
      "attributeValueArray": [
        0,
        0,
        0,
        0,
        0
      ],
      "tagDataArray": [],
      "wordDataArray": [
        {
          "patternID": 0,
          "eventID": 7,
          "tagIndex": -1,
          "tagValue": 0.0,
          "str": "Changements de tenue (%)",
          "strWidth": 352.890625
        }
      ]
    },
    {
      "labelIndex": 7,
      "arrayIndex": 7,
      "labelName": "SS_xmenu_net_16",
      "styleInfo": {
        "styleIndex": 50,
        "colorIndex": -1,
        "fontSize": 42,
        "maxWidth": 756,
        "controlID": 0
      },
      "attributeValueArray": [
        0,
        0,
        0,
        0,
        0
      ],
      "tagDataArray": [],
      "wordDataArray": [
        {
          "patternID": 0,
          "eventID": 7,
          "tagIndex": -1,
          "tagValue": 0.0,
          "str": "Objets cachés découverts (%)",
          "strWidth": 385.78125
        }
      ]
    },
    {
      "labelIndex": 8,
      "arrayIndex": 8,
      "labelName": "SS_xmenu_net_17",
      "styleInfo": {
        "styleIndex": 50,
        "colorIndex": -1,
        "fontSize": 42,
        "maxWidth": 756,
        "controlID": 0
      },
      "attributeValueArray": [
        0,
        0,
        0,
        0,
        0
      ],
      "tagDataArray": [],
      "wordDataArray": [
        {
          "patternID": 0,
          "eventID": 7,
          "tagIndex": -1,
          "tagValue": 0.0,
          "str": "Sifflements avec les doigts (%)",
          "strWidth": 397.015625
        }
      ]
    },
    {
      "labelIndex": 9,
      "arrayIndex": 9,
      "labelName": "SS_xmenu_net_18",
      "styleInfo": {
        "styleIndex": 46,
        "colorIndex": -1,
        "fontSize": 42,
        "maxWidth": 588,
        "controlID": 0
      },
      "attributeValueArray": [
        0,
        0,
        0,
        0,
        0
      ],
      "tagDataArray": [],
      "wordDataArray": [
        {
          "patternID": 0,
          "eventID": 7,
          "tagIndex": -1,
          "tagValue": 0.0,
          "str": "Stade de Combat",
          "strWidth": 227.359375
        }
      ]
    },
    {
      "labelIndex": 10,
      "arrayIndex": 10,
      "labelName": "SS_xmenu_net_19",
      "styleInfo": {
        "styleIndex": 46,
        "colorIndex": -1,
        "fontSize": 42,
        "maxWidth": 588,
        "controlID": 0
      },
      "attributeValueArray": [
        0,
        0,
        0,
        0,
        0
      ],
      "tagDataArray": [],
      "wordDataArray": [
        {
          "patternID": 0,
          "eventID": 7,
          "tagIndex": -1,
          "tagValue": 0.0,
          "str": "Compétition live",
          "strWidth": 215.5
        }
      ]
    },
    {
      "labelIndex": 11,
      "arrayIndex": 11,
      "labelName": "SS_xmenu_net_20",
      "styleInfo": {
        "styleIndex": 50,
        "colorIndex": -1,
        "fontSize": 42,
        "maxWidth": 756,
        "controlID": 0
      },
      "attributeValueArray": [
        0,
        0,
        0,
        0,
        0
      ],
      "tagDataArray": [],
      "wordDataArray": [
        {
          "patternID": 0,
          "eventID": 7,
          "tagIndex": -1,
          "tagValue": 0.0,
          "str": "Joueurs comptabilisés",
          "strWidth": 282.4375
        }
      ]
    },
    {
      "labelIndex": 12,
      "arrayIndex": 12,
      "labelName": "SS_xmenu_net_21",
      "styleInfo": {
        "styleIndex": 148,
        "colorIndex": -1,
        "fontSize": 42,
        "maxWidth": 168,
        "controlID": 0
      },
      "attributeValueArray": [
        0,
        0,
        0,
        0,
        0
      ],
      "tagDataArray": [
        {
          "tagIndex": 0,
          "groupID": 2,
          "tagID": 2,
          "tagPatternID": 1,
          "forceArticle": 0,
          "tagParameter": 205,
          "tagWordArray": [],
          "forceGrmID": 0
        }
      ],
      "wordDataArray": [
        {
          "patternID": 5,
          "eventID": 7,
          "tagIndex": 0,
          "tagValue": 0.0,
          "str": "",
          "strWidth": -1.0
        }
      ]
    },
    {
      "labelIndex": 13,
      "arrayIndex": 13,
      "labelName": "SS_xmenu_net_23",
      "styleInfo": {
        "styleIndex": 148,
        "colorIndex": -1,
        "fontSize": 42,
        "maxWidth": 168,
        "controlID": 0
      },
      "attributeValueArray": [
        0,
        0,
        0,
        0,
        0
      ],
      "tagDataArray": [
        {
          "tagIndex": 0,
          "groupID": 2,
          "tagID": 2,
          "tagPatternID": 1,
          "forceArticle": 0,
          "tagParameter": 205,
          "tagWordArray": [],
          "forceGrmID": 0
        }
      ],
      "wordDataArray": [
        {
          "patternID": 5,
          "eventID": 7,
          "tagIndex": 0,
          "tagValue": 0.0,
          "str": "",
          "strWidth": -1.0
        }
      ]
    },
    {
      "labelIndex": 14,
      "arrayIndex": 14,
      "labelName": "SS_xmenu_net_24",
      "styleInfo": {
        "styleIndex": 83,
        "colorIndex": -1,
        "fontSize": 32,
        "maxWidth": 320,
        "controlID": 0
      },
      "attributeValueArray": [
        0,
        0,
        0,
        0,
        0
      ],
      "tagDataArray": [],
      "wordDataArray": [
        {
          "patternID": 0,
          "eventID": 7,
          "tagIndex": -1,
          "tagValue": 0.0,
          "str": " Retour",
          "strWidth": 94.703125
        }
      ]
    },
    {
      "labelIndex": 15,
      "arrayIndex": 15,
      "labelName": "SS_xmenu_net_25",
      "styleInfo": {
        "styleIndex": 12,
        "colorIndex": -1,
        "fontSize": 54,
        "maxWidth": 756,
        "controlID": 0
      },
      "attributeValueArray": [
        0,
        0,
        0,
        0,
        0
      ],
      "tagDataArray": [],
      "wordDataArray": [
        {
          "patternID": 0,
          "eventID": 7,
          "tagIndex": -1,
          "tagValue": 0.0,
          "str": "Oui",
          "strWidth": 47.578125
        }
      ]
    },
    {
      "labelIndex": 16,
      "arrayIndex": 16,
      "labelName": "SS_xmenu_net_26",
      "styleInfo": {
        "styleIndex": 12,
        "colorIndex": -1,
        "fontSize": 54,
        "maxWidth": 756,
        "controlID": 0
      },
      "attributeValueArray": [
        0,
        0,
        0,
        0,
        0
      ],
      "tagDataArray": [],
      "wordDataArray": [
        {
          "patternID": 0,
          "eventID": 7,
          "tagIndex": -1,
          "tagValue": 0.0,
          "str": "Non",
          "strWidth": 54.359375
        }
      ]
    },
    {
      "labelIndex": 17,
      "arrayIndex": 17,
      "labelName": "SS_xmenu_net_27",
      "styleInfo": {
        "styleIndex": 83,
        "colorIndex": -1,
        "fontSize": 32,
        "maxWidth": 320,
        "controlID": 0
      },
      "attributeValueArray": [
        0,
        0,
        0,
        0,
        0
      ],
      "tagDataArray": [],
      "wordDataArray": [
        {
          "patternID": 0,
          "eventID": 7,
          "tagIndex": -1,
          "tagValue": 0.0,
          "str": " Sélectionner",
          "strWidth": 169.390625
        }
      ]
    },
    {
      "labelIndex": 18,
      "arrayIndex": 18,
      "labelName": "SS_xmenu_net_28",
      "styleInfo": {
        "styleIndex": 58,
        "colorIndex": -1,
        "fontSize": 42,
        "maxWidth": 840,
        "controlID": 0
      },
      "attributeValueArray": [
        0,
        0,
        0,
        0,
        0
      ],
      "tagDataArray": [],
      "wordDataArray": [
        {
          "patternID": 7,
          "eventID": 1,
          "tagIndex": -1,
          "tagValue": 0.0,
          "str": "Récupération des données sur les joueurs",
          "strWidth": 533.65625
        },
        {
          "patternID": 0,
          "eventID": 7,
          "tagIndex": -1,
          "tagValue": 0.0,
          "str": "croisés en communication sans fil locale...",
          "strWidth": 537.9531
        }
      ]
    },
    {
      "labelIndex": 19,
      "arrayIndex": 19,
      "labelName": "SS_xmenu_net_29",
      "styleInfo": {
        "styleIndex": 58,
        "colorIndex": -1,
        "fontSize": 42,
        "maxWidth": 840,
        "controlID": 0
      },
      "attributeValueArray": [
        0,
        0,
        0,
        0,
        0
      ],
      "tagDataArray": [],
      "wordDataArray": [
        {
          "patternID": 7,
          "eventID": 1,
          "tagIndex": -1,
          "tagValue": 0.0,
          "str": "Récupération des données sur les joueurs",
          "strWidth": 533.65625
        },
        {
          "patternID": 0,
          "eventID": 7,
          "tagIndex": -1,
          "tagValue": 0.0,
          "str": "croisés en ligne...",
          "strWidth": 223.109375
        }
      ]
    },
    {
      "labelIndex": 20,
      "arrayIndex": 20,
      "labelName": "SS_xmenu_net_30",
      "styleInfo": {
        "styleIndex": 0,
        "colorIndex": -1,
        "fontSize": 54,
        "maxWidth": 1080,
        "controlID": 0
      },
      "attributeValueArray": [
        0,
        0,
        0,
        0,
        0
      ],
      "tagDataArray": [],
      "wordDataArray": [
        {
          "patternID": 7,
          "eventID": 3,
          "tagIndex": -1,
          "tagValue": 0.0,
          "str": "Vous allez maintenant vous connecter à Internet.",
          "strWidth": 630.4844
        },
        {
          "patternID": 7,
          "eventID": 1,
          "tagIndex": -1,
          "tagValue": 0.0,
          "str": "Votre partie va être sauvegardée.",
          "strWidth": 435.0625
        },
        {
          "patternID": 0,
          "eventID": 7,
          "tagIndex": -1,
          "tagValue": 0.0,
          "str": "Voulez-vous continuer ?",
          "strWidth": 311.984375
        }
      ]
    },
    {
      "labelIndex": 21,
      "arrayIndex": 21,
      "labelName": "SS_xmenu_net_31",
      "styleInfo": {
        "styleIndex": 20,
        "colorIndex": -1,
        "fontSize": 54,
        "maxWidth": 1080,
        "controlID": 0
      },
      "attributeValueArray": [
        0,
        0,
        0,
        0,
        0
      ],
      "tagDataArray": [],
      "wordDataArray": [
        {
          "patternID": 7,
          "eventID": 1,
          "tagIndex": -1,
          "tagValue": 0.0,
          "str": "Connexion en cours...",
          "strWidth": 279.8125
        },
        {
          "patternID": 0,
          "eventID": 7,
          "tagIndex": -1,
          "tagValue": 0.0,
          "str": "Veuillez patienter.",
          "strWidth": 237.71875
        }
      ]
    },
    {
      "labelIndex": 22,
      "arrayIndex": 22,
      "labelName": "SS_xmenu_net_32",
      "styleInfo": {
        "styleIndex": 0,
        "colorIndex": -1,
        "fontSize": 54,
        "maxWidth": 1080,
        "controlID": 0
      },
      "attributeValueArray": [
        0,
        0,
        0,
        0,
        0
      ],
      "tagDataArray": [],
      "wordDataArray": [
        {
          "patternID": 7,
          "eventID": 7,
          "tagIndex": -1,
          "tagValue": 0.0,
          "str": "Connexion à Internet établie.",
          "strWidth": 379.71875
        }
      ]
    },
    {
      "labelIndex": 23,
      "arrayIndex": 23,
      "labelName": "SS_xmenu_net_33",
      "styleInfo": {
        "styleIndex": 20,
        "colorIndex": -1,
        "fontSize": 54,
        "maxWidth": 1080,
        "controlID": 0
      },
      "attributeValueArray": [
        0,
        0,
        0,
        0,
        0
      ],
      "tagDataArray": [],
      "wordDataArray": [
        {
          "patternID": 7,
          "eventID": 1,
          "tagIndex": -1,
          "tagValue": 0.0,
          "str": "Sauvegarde en cours...",
          "strWidth": 291.234375
        },
        {
          "patternID": 0,
          "eventID": 7,
          "tagIndex": -1,
          "tagValue": 0.0,
          "str": "Veuillez patienter.",
          "strWidth": 237.71875
        }
      ]
    },
    {
      "labelIndex": 24,
      "arrayIndex": 24,
      "labelName": "SS_xmenu_net_34",
      "styleInfo": {
        "styleIndex": 20,
        "colorIndex": -1,
        "fontSize": 54,
        "maxWidth": 1080,
        "controlID": 0
      },
      "attributeValueArray": [
        0,
        0,
        0,
        0,
        0
      ],
      "tagDataArray": [],
      "wordDataArray": [
        {
          "patternID": 7,
          "eventID": 7,
          "tagIndex": -1,
          "tagValue": 0.0,
          "str": "Connexion à Internet activée.",
          "strWidth": 382.71875
        }
      ]
    },
    {
      "labelIndex": 25,
      "arrayIndex": 25,
      "labelName": "SS_xmenu_net_35",
      "styleInfo": {
        "styleIndex": 0,
        "colorIndex": -1,
        "fontSize": 54,
        "maxWidth": 1080,
        "controlID": 0
      },
      "attributeValueArray": [
        0,
        0,
        0,
        0,
        0
      ],
      "tagDataArray": [],
      "wordDataArray": [
        {
          "patternID": 0,
          "eventID": 7,
          "tagIndex": -1,
          "tagValue": 0.0,
          "str": "Voulez-vous vous déconnecter d’Internet ?",
          "strWidth": 554.9844
        }
      ]
    },
    {
      "labelIndex": 26,
      "arrayIndex": 26,
      "labelName": "SS_xmenu_net_36",
      "styleInfo": {
        "styleIndex": 20,
        "colorIndex": -1,
        "fontSize": 54,
        "maxWidth": 1080,
        "controlID": 0
      },
      "attributeValueArray": [
        0,
        0,
        0,
        0,
        0
      ],
      "tagDataArray": [],
      "wordDataArray": [
        {
          "patternID": 7,
          "eventID": 1,
          "tagIndex": -1,
          "tagValue": 0.0,
          "str": "Déconnexion en cours...",
          "strWidth": 311.59375
        },
        {
          "patternID": 0,
          "eventID": 7,
          "tagIndex": -1,
          "tagValue": 0.0,
          "str": "Veuillez patienter.",
          "strWidth": 237.71875
        }
      ]
    },
    {
      "labelIndex": 27,
      "arrayIndex": 27,
      "labelName": "SS_xmenu_net_37",
      "styleInfo": {
        "styleIndex": 20,
        "colorIndex": -1,
        "fontSize": 54,
        "maxWidth": 1080,
        "controlID": 0
      },
      "attributeValueArray": [
        0,
        0,
        0,
        0,
        0
      ],
      "tagDataArray": [],
      "wordDataArray": [
        {
          "patternID": 7,
          "eventID": 7,
          "tagIndex": -1,
          "tagValue": 0.0,
          "str": "Communication sans fil locale activée.",
          "strWidth": 493.765625
        }
      ]
    }
  ]
}